# pyc_path: C:/Users/renan/OneDrive/Documents/New Era Glasses/src/new_era/application/services/__pycache__/__init__.cpython-312.pyc
# embedded_filename: C:\Users\renan\OneDrive\Documents\New Era Glasses\src\new_era\application\services\__init__.py
# module_name: new_era.application.services.__init__
# first_line: 1
# compiled_at: 2026-05-23T21:54:12+00:00
# source_size: 385

## code_object: <module>
filename: C:\Users\renan\OneDrive\Documents\New Era Glasses\src\new_era\application\services\__init__.py
first_line: 1
argcount: 0
locals: 0
stacksize: 2
flags: 0
names: ['__doc__', 'new_era.application.services.document_session', 'DocumentSessionService', 'new_era.application.services.grocery_session', 'GrocerySessionService', 'new_era.application.services.simulation_runtime', 'SimulationRuntime', '__all__']
varnames: []
cellvars: []
freevars: []
disassembly:
  0           0 RESUME                   0

  1           2 LOAD_CONST               0 ('Application services for feature-oriented entry points.')
              4 STORE_NAME               0 (__doc__)

  3           6 LOAD_CONST               1 (0)
              8 LOAD_CONST               2 (('DocumentSessionService',))
             10 IMPORT_NAME              1 (new_era.application.services.document_session)
             12 IMPORT_FROM              2 (DocumentSessionService)
             14 STORE_NAME               2 (DocumentSessionService)
             16 POP_TOP

  4          18 LOAD_CONST               1 (0)
             20 LOAD_CONST               3 (('GrocerySessionService',))
             22 IMPORT_NAME              3 (new_era.application.services.grocery_session)
             24 IMPORT_FROM              4 (GrocerySessionService)
             26 STORE_NAME               4 (GrocerySessionService)
             28 POP_TOP

  5          30 LOAD_CONST               1 (0)
             32 LOAD_CONST               4 (('SimulationRuntime',))
             34 IMPORT_NAME              5 (new_era.application.services.simulation_runtime)
             36 IMPORT_FROM              6 (SimulationRuntime)
             38 STORE_NAME               6 (SimulationRuntime)
             40 POP_TOP

  7          42 BUILD_LIST               0
             44 LOAD_CONST               5 (('DocumentSessionService', 'GrocerySessionService', 'SimulationRuntime'))
             46 LIST_EXTEND              1
             48 STORE_NAME               7 (__all__)
             50 RETURN_CONST             6 (None)

