# pyc_path: C:/Users/renan/OneDrive/Documents/New Era Glasses/src/new_era/application/use_cases/__pycache__/get_session_trace.cpython-312.pyc
# embedded_filename: C:\Users\renan\OneDrive\Documents\New Era Glasses\src\new_era\application\use_cases\get_session_trace.py
# module_name: new_era.application.use_cases.get_session_trace
# first_line: 1
# compiled_at: 2026-05-24T15:01:48+00:00
# source_size: 10153

## code_object: <module>
filename: C:\Users\renan\OneDrive\Documents\New Era Glasses\src\new_era\application\use_cases\get_session_trace.py
first_line: 1
argcount: 0
locals: 0
stacksize: 8
flags: 16777216
names: ['__future__', 'annotations', 'base64', 'urlsafe_b64decode', 'urlsafe_b64encode', 'dataclasses', 'dataclass', 'datetime', 'new_era.application.ports', 'EventStore', 'new_era.domain.events', 'Event', 'EventType', 'DEFAULT_TRACE_LIMIT', 'MAX_TRACE_LIMIT', 'SessionTraceEntry', 'SessionTraceReadModel', 'build_trace_title', 'build_trace_detail', 'build_trace_step', 'OBSERVATION_CREATED', 'ALERT_CANDIDATE_CREATED', 'ALERT_SHOWN', 'ALERT_SUPPRESSED', 'LENS_COMMAND_DELIVERED', 'DEVICE_CAPABILITY_MISSING', 'DEVICE_DELIVERY_FAILED', 'JOB_STARTED', 'JOB_STATUS_UPDATED', 'JOB_COMPLETED', 'JOB_FAILED', 'AI_CALL_FAILED', 'ALERT_FEEDBACK_GIVEN', 'TRACE_STEP_EVENT_TYPES', '__annotations__', 'normalize_trace_limit', 'encode_trace_cursor', 'decode_trace_cursor', 'event_types_for_steps', 'combine_event_type_filters', 'GetSessionTrace']
varnames: []
cellvars: []
freevars: []
disassembly:
  0           0 RESUME                   0

  1           2 SETUP_ANNOTATIONS
              4 LOAD_CONST               0 (0)
              6 LOAD_CONST               1 (('annotations',))
              8 IMPORT_NAME              0 (__future__)
             10 IMPORT_FROM              1 (annotations)
             12 STORE_NAME               1 (annotations)
             14 POP_TOP

  3          16 LOAD_CONST               0 (0)
             18 LOAD_CONST               2 (('urlsafe_b64decode', 'urlsafe_b64encode'))
             20 IMPORT_NAME              2 (base64)
             22 IMPORT_FROM              3 (urlsafe_b64decode)
             24 STORE_NAME               3 (urlsafe_b64decode)
             26 IMPORT_FROM              4 (urlsafe_b64encode)
             28 STORE_NAME               4 (urlsafe_b64encode)
             30 POP_TOP

  4          32 LOAD_CONST               0 (0)
             34 LOAD_CONST               3 (('dataclass',))
             36 IMPORT_NAME              5 (dataclasses)
             38 IMPORT_FROM              6 (dataclass)
             40 STORE_NAME               6 (dataclass)
             42 POP_TOP

  5          44 LOAD_CONST               0 (0)
             46 LOAD_CONST               4 (('datetime',))
             48 IMPORT_NAME              7 (datetime)
             50 IMPORT_FROM              7 (datetime)
             52 STORE_NAME               7 (datetime)
             54 POP_TOP

  7          56 LOAD_CONST               0 (0)
             58 LOAD_CONST               5 (('EventStore',))
             60 IMPORT_NAME              8 (new_era.application.ports)
             62 IMPORT_FROM              9 (EventStore)
             64 STORE_NAME               9 (EventStore)
             66 POP_TOP

  8          68 LOAD_CONST               0 (0)
             70 LOAD_CONST               6 (('Event', 'EventType'))
             72 IMPORT_NAME             10 (new_era.domain.events)
             74 IMPORT_FROM             11 (Event)
             76 STORE_NAME              11 (Event)
             78 IMPORT_FROM             12 (EventType)
             80 STORE_NAME              12 (EventType)
             82 POP_TOP

 10          84 LOAD_CONST               7 (50)
             86 STORE_NAME              13 (DEFAULT_TRACE_LIMIT)

 11          88 LOAD_CONST               8 (100)
             90 STORE_NAME              14 (MAX_TRACE_LIMIT)

 14          92 PUSH_NULL
             94 LOAD_NAME                6 (dataclass)
             96 LOAD_CONST               9 (True)
             98 LOAD_CONST               9 (True)
            100 KW_NAMES                10 (('frozen', 'slots'))
            102 CALL                     2

 15         110 PUSH_NULL
            112 LOAD_BUILD_CLASS
            114 LOAD_CONST              11 (<code object SessionTraceEntry at 0x000001494112CFF0, file "C:\Users\renan\OneDrive\Documents\New Era Glasses\src\new_era\application\use_cases\get_session_trace.py", line 14>)
            116 MAKE_FUNCTION            0
            118 LOAD_CONST              12 ('SessionTraceEntry')
            120 CALL                     2

 14         128 CALL                     0

 15         136 STORE_NAME              15 (SessionTraceEntry)

 34         138 PUSH_NULL
            140 LOAD_NAME                6 (dataclass)
            142 LOAD_CONST               9 (True)
            144 LOAD_CONST               9 (True)
            146 KW_NAMES                10 (('frozen', 'slots'))
            148 CALL                     2

 35         156 PUSH_NULL
            158 LOAD_BUILD_CLASS
            160 LOAD_CONST              13 (<code object SessionTraceReadModel at 0x000001494106A780, file "C:\Users\renan\OneDrive\Documents\New Era Glasses\src\new_era\application\use_cases\get_session_trace.py", line 34>)
            162 MAKE_FUNCTION            0
            164 LOAD_CONST              14 ('SessionTraceReadModel')
            166 CALL                     2

 34         174 CALL                     0

 35         182 STORE_NAME              16 (SessionTraceReadModel)

 52         184 LOAD_CONST              29 (('event', 'Event', 'return', 'str'))
            186 LOAD_CONST              15 (<code object build_trace_title at 0x0000014941269BB0, file "C:\Users\renan\OneDrive\Documents\New Era Glasses\src\new_era\application\use_cases\get_session_trace.py", line 52>)
            188 MAKE_FUNCTION            4 (annotations)
            190 STORE_NAME              17 (build_trace_title)

 82         192 LOAD_CONST              29 (('event', 'Event', 'return', 'str'))
            194 LOAD_CONST              16 (<code object build_trace_detail at 0x000001494120A320, file "C:\Users\renan\OneDrive\Documents\New Era Glasses\src\new_era\application\use_cases\get_session_trace.py", line 82>)
            196 MAKE_FUNCTION            4 (annotations)
            198 STORE_NAME              18 (build_trace_detail)

127         200 LOAD_CONST              30 (('event_type', 'EventType', 'return', 'str'))
            202 LOAD_CONST              17 (<code object build_trace_step at 0x000001494126DD20, file "C:\Users\renan\OneDrive\Documents\New Era Glasses\src\new_era\application\use_cases\get_session_trace.py", line 127>)
            204 MAKE_FUNCTION            4 (annotations)
            206 STORE_NAME              19 (build_trace_step)

155         208 LOAD_NAME               12 (EventType)
            210 LOAD_ATTR               40 (OBSERVATION_CREATED)
            230 BUILD_SET                1

156         232 LOAD_NAME               12 (EventType)
            234 LOAD_ATTR               42 (ALERT_CANDIDATE_CREATED)
            254 BUILD_SET                1

157         256 LOAD_NAME               12 (EventType)
            258 LOAD_ATTR               44 (ALERT_SHOWN)
            278 LOAD_NAME               12 (EventType)
            280 LOAD_ATTR               46 (ALERT_SUPPRESSED)
            300 BUILD_SET                2

159         302 LOAD_NAME               12 (EventType)
            304 LOAD_ATTR               48 (LENS_COMMAND_DELIVERED)

160         324 LOAD_NAME               12 (EventType)
            326 LOAD_ATTR               50 (DEVICE_CAPABILITY_MISSING)

161         346 LOAD_NAME               12 (EventType)
            348 LOAD_ATTR               52 (DEVICE_DELIVERY_FAILED)

158         368 BUILD_SET                3

164         370 LOAD_NAME               12 (EventType)
            372 LOAD_ATTR               54 (JOB_STARTED)

165         392 LOAD_NAME               12 (EventType)
            394 LOAD_ATTR               56 (JOB_STATUS_UPDATED)

166         414 LOAD_NAME               12 (EventType)
            416 LOAD_ATTR               58 (JOB_COMPLETED)

167         436 LOAD_NAME               12 (EventType)
            438 LOAD_ATTR               60 (JOB_FAILED)

163         458 BUILD_SET                4

169         460 LOAD_NAME               12 (EventType)
            462 LOAD_ATTR               62 (AI_CALL_FAILED)
            482 BUILD_SET                1

170         484 LOAD_NAME               12 (EventType)
            486 LOAD_ATTR               64 (ALERT_FEEDBACK_GIVEN)
            506 BUILD_SET                1

154         508 LOAD_CONST              18 (('observation', 'candidate', 'decision', 'delivery', 'job', 'provider', 'feedback'))
            510 BUILD_CONST_KEY_MAP      7
            512 STORE_NAME              33 (TRACE_STEP_EVENT_TYPES)
            514 LOAD_CONST              19 ('dict[str, set[EventType]]')
            516 LOAD_NAME               34 (__annotations__)
            518 LOAD_CONST              20 ('TRACE_STEP_EVENT_TYPES')
            520 STORE_SUBSCR

174         524 LOAD_CONST              31 (('limit', 'int | None', 'return', 'int'))
            526 LOAD_CONST              21 (<code object normalize_trace_limit at 0x000001494112D110, file "C:\Users\renan\OneDrive\Documents\New Era Glasses\src\new_era\application\use_cases\get_session_trace.py", line 174>)
            528 MAKE_FUNCTION            4 (annotations)
            530 STORE_NAME              35 (normalize_trace_limit)

182         532 LOAD_CONST              29 (('event', 'Event', 'return', 'str'))
            534 LOAD_CONST              22 (<code object encode_trace_cursor at 0x0000014941079A10, file "C:\Users\renan\OneDrive\Documents\New Era Glasses\src\new_era\application\use_cases\get_session_trace.py", line 182>)
            536 MAKE_FUNCTION            4 (annotations)
            538 STORE_NAME              36 (encode_trace_cursor)

187         540 LOAD_CONST              32 (('cursor', 'str | None', 'return', 'tuple[datetime, str] | None'))
            542 LOAD_CONST              23 (<code object decode_trace_cursor at 0x0000014940CCE3A0, file "C:\Users\renan\OneDrive\Documents\New Era Glasses\src\new_era\application\use_cases\get_session_trace.py", line 187>)
            544 MAKE_FUNCTION            4 (annotations)
            546 STORE_NAME              37 (decode_trace_cursor)

198         548 LOAD_CONST              33 (('steps', 'set[str] | None', 'return', 'set[EventType] | None'))
            550 LOAD_CONST              24 (<code object event_types_for_steps at 0x0000014941124030, file "C:\Users\renan\OneDrive\Documents\New Era Glasses\src\new_era\application\use_cases\get_session_trace.py", line 198>)
            552 MAKE_FUNCTION            4 (annotations)
            554 STORE_NAME              38 (event_types_for_steps)

212         556 NOP

214         558 NOP

212         560 NOP

215         562 NOP

212         564 NOP

216         566 NOP

212         568 LOAD_CONST              34 (('event_types', 'set[EventType] | None', 'steps', 'set[str] | None', 'return', 'set[EventType] | None'))
            570 LOAD_CONST              25 (<code object combine_event_type_filters at 0x0000014941148470, file "C:\Users\renan\OneDrive\Documents\New Era Glasses\src\new_era\application\use_cases\get_session_trace.py", line 212>)
            572 MAKE_FUNCTION            4 (annotations)
            574 STORE_NAME              39 (combine_event_type_filters)

225         576 PUSH_NULL
            578 LOAD_NAME                6 (dataclass)
            580 LOAD_CONST               9 (True)
            582 LOAD_CONST               9 (True)
            584 KW_NAMES                10 (('frozen', 'slots'))
            586 CALL                     2

226         594 PUSH_NULL
            596 LOAD_BUILD_CLASS
            598 LOAD_CONST              26 (<code object GetSessionTrace at 0x000001494112D470, file "C:\Users\renan\OneDrive\Documents\New Era Glasses\src\new_era\application\use_cases\get_session_trace.py", line 225>)
            600 MAKE_FUNCTION            0
            602 LOAD_CONST              27 ('GetSessionTrace')
            604 CALL                     2

225         612 CALL                     0

226         620 STORE_NAME              40 (GetSessionTrace)
            622 RETURN_CONST            28 (None)

Disassembly of <code object SessionTraceEntry at 0x000001494112CFF0, file "C:\Users\renan\OneDrive\Documents\New Era Glasses\src\new_era\application\use_cases\get_session_trace.py", line 14>:
 14           0 RESUME                   0
              2 LOAD_NAME                0 (__name__)
              4 STORE_NAME               1 (__module__)
              6 LOAD_CONST               0 ('SessionTraceEntry')
              8 STORE_NAME               2 (__qualname__)
             10 SETUP_ANNOTATIONS

 16          12 LOAD_CONST               1 ('str')
             14 LOAD_NAME                3 (__annotations__)
             16 LOAD_CONST               2 ('event_id')
             18 STORE_SUBSCR

 17          22 LOAD_CONST               1 ('str')
             24 LOAD_NAME                3 (__annotations__)
             26 LOAD_CONST               3 ('event_type')
             28 STORE_SUBSCR

 18          32 LOAD_CONST               1 ('str')
             34 LOAD_NAME                3 (__annotations__)
             36 LOAD_CONST               4 ('step')
             38 STORE_SUBSCR

 19          42 LOAD_CONST               1 ('str')
             44 LOAD_NAME                3 (__annotations__)
             46 LOAD_CONST               5 ('title')
             48 STORE_SUBSCR

 20          52 LOAD_CONST               1 ('str')
             54 LOAD_NAME                3 (__annotations__)
             56 LOAD_CONST               6 ('detail')
             58 STORE_SUBSCR

 21          62 LOAD_CONST               1 ('str')
             64 LOAD_NAME                3 (__annotations__)
             66 LOAD_CONST               7 ('created_at')
             68 STORE_SUBSCR

 23          72 LOAD_CONST              10 (('return', 'dict[str, object]'))
             74 LOAD_CONST               8 (<code object to_dict at 0x000001494104E790, file "C:\Users\renan\OneDrive\Documents\New Era Glasses\src\new_era\application\use_cases\get_session_trace.py", line 23>)
             76 MAKE_FUNCTION            4 (annotations)
             78 STORE_NAME               4 (to_dict)
             80 RETURN_CONST             9 (None)

Disassembly of <code object to_dict at 0x000001494104E790, file "C:\Users\renan\OneDrive\Documents\New Era Glasses\src\new_era\application\use_cases\get_session_trace.py", line 23>:
 23           0 RESUME                   0

 25           2 LOAD_FAST                0 (self)
              4 LOAD_ATTR                0 (event_id)

 26          24 LOAD_FAST                0 (self)
             26 LOAD_ATTR                2 (event_type)

 27          46 LOAD_FAST                0 (self)
             48 LOAD_ATTR                4 (step)

 28          68 LOAD_FAST                0 (self)
             70 LOAD_ATTR                6 (title)

 29          90 LOAD_FAST                0 (self)
             92 LOAD_ATTR                8 (detail)

 30         112 LOAD_FAST                0 (self)
            114 LOAD_ATTR               10 (created_at)

 24         134 LOAD_CONST               1 (('event_id', 'event_type', 'step', 'title', 'detail', 'created_at'))
            136 BUILD_CONST_KEY_MAP      6
            138 RETURN_VALUE

Disassembly of <code object SessionTraceReadModel at 0x000001494106A780, file "C:\Users\renan\OneDrive\Documents\New Era Glasses\src\new_era\application\use_cases\get_session_trace.py", line 34>:
 34           0 RESUME                   0
              2 LOAD_NAME                0 (__name__)
              4 STORE_NAME               1 (__module__)
              6 LOAD_CONST               0 ('SessionTraceReadModel')
              8 STORE_NAME               2 (__qualname__)
             10 SETUP_ANNOTATIONS

 36          12 LOAD_CONST               1 ('str')
             14 LOAD_NAME                3 (__annotations__)
             16 LOAD_CONST               2 ('session_id')
             18 STORE_SUBSCR

 37          22 LOAD_CONST               3 ('str | None')
             24 LOAD_NAME                3 (__annotations__)
             26 LOAD_CONST               4 ('trace_id')
             28 STORE_SUBSCR

 38          32 LOAD_CONST               5 ('int')
             34 LOAD_NAME                3 (__annotations__)
             36 LOAD_CONST               6 ('event_count')
             38 STORE_SUBSCR

 39          42 LOAD_CONST               3 ('str | None')
             44 LOAD_NAME                3 (__annotations__)
             46 LOAD_CONST               7 ('next_cursor')
             48 STORE_SUBSCR

 40          52 LOAD_CONST               8 ('tuple[SessionTraceEntry, ...]')
             54 LOAD_NAME                3 (__annotations__)
             56 LOAD_CONST               9 ('session_trace')
             58 STORE_SUBSCR

 42          62 LOAD_CONST              12 (('return', 'dict[str, object]'))
             64 LOAD_CONST              10 (<code object to_dict at 0x00000149411381B0, file "C:\Users\renan\OneDrive\Documents\New Era Glasses\src\new_era\application\use_cases\get_session_trace.py", line 42>)
             66 MAKE_FUNCTION            4 (annotations)
             68 STORE_NAME               4 (to_dict)
             70 RETURN_CONST            11 (None)

Disassembly of <code object to_dict at 0x00000149411381B0, file "C:\Users\renan\OneDrive\Documents\New Era Glasses\src\new_era\application\use_cases\get_session_trace.py", line 42>:
 42           0 RESUME                   0

 44           2 LOAD_FAST                0 (self)
              4 LOAD_ATTR                0 (session_id)

 45          24 LOAD_FAST                0 (self)
             26 LOAD_ATTR                2 (trace_id)

 46          46 LOAD_FAST                0 (self)
             48 LOAD_ATTR                4 (event_count)

 47          68 LOAD_FAST                0 (self)
             70 LOAD_ATTR                6 (next_cursor)

 48          90 LOAD_FAST                0 (self)
             92 LOAD_ATTR                8 (session_trace)
            112 GET_ITER
            114 LOAD_FAST_AND_CLEAR      1 (entry)
            116 SWAP                     2
            118 BUILD_LIST               0
            120 SWAP                     2
        >>  122 FOR_ITER                18 (to 162)
            126 STORE_FAST               1 (entry)
            128 LOAD_FAST                1 (entry)
            130 LOAD_ATTR               11 (NULL|self + to_dict)
            150 CALL                     0
            158 LIST_APPEND              2
            160 JUMP_BACKWARD           20 (to 122)
        >>  162 END_FOR
            164 SWAP                     2
            166 STORE_FAST               1 (entry)

 43         168 LOAD_CONST               1 (('session_id', 'trace_id', 'event_count', 'next_cursor', 'session_trace'))
            170 BUILD_CONST_KEY_MAP      5
            172 RETURN_VALUE
        >>  174 SWAP                     2
            176 POP_TOP

 48         178 SWAP                     2
            180 STORE_FAST               1 (entry)
            182 RERAISE                  0
ExceptionTable:
  118 to 162 -> 174 [6]

Disassembly of <code object build_trace_title at 0x0000014941269BB0, file "C:\Users\renan\OneDrive\Documents\New Era Glasses\src\new_era\application\use_cases\get_session_trace.py", line 52>:
 52           0 RESUME                   0

 53           2 LOAD_FAST                0 (event)
              4 LOAD_ATTR                0 (event_type)
             24 LOAD_GLOBAL              2 (EventType)
             34 LOAD_ATTR                4 (OBSERVATION_CREATED)
             54 COMPARE_OP              40 (==)
             58 POP_JUMP_IF_FALSE        1 (to 62)

 54          60 RETURN_CONST             1 ('Observation captured')

 55     >>   62 LOAD_FAST                0 (event)
             64 LOAD_ATTR                0 (event_type)
             84 LOAD_GLOBAL              2 (EventType)
             94 LOAD_ATTR                6 (ALERT_CANDIDATE_CREATED)
            114 COMPARE_OP              40 (==)
            118 POP_JUMP_IF_FALSE        1 (to 122)

 56         120 RETURN_CONST             2 ('Alert candidate created')

 57     >>  122 LOAD_FAST                0 (event)
            124 LOAD_ATTR                0 (event_type)
            144 LOAD_GLOBAL              2 (EventType)
            154 LOAD_ATTR                8 (ALERT_SHOWN)
            174 COMPARE_OP              40 (==)
            178 POP_JUMP_IF_FALSE        1 (to 182)

 58         180 RETURN_CONST             3 ('Attention policy allowed display')

 59     >>  182 LOAD_FAST                0 (event)
            184 LOAD_ATTR                0 (event_type)
            204 LOAD_GLOBAL              2 (EventType)
            214 LOAD_ATTR               10 (ALERT_SUPPRESSED)
            234 COMPARE_OP              40 (==)
            238 POP_JUMP_IF_FALSE        1 (to 242)

 60         240 RETURN_CONST             4 ('Attention policy suppressed alert')

 61     >>  242 LOAD_FAST                0 (event)
            244 LOAD_ATTR                0 (event_type)
            264 LOAD_GLOBAL              2 (EventType)
            274 LOAD_ATTR               12 (LENS_COMMAND_DELIVERED)
            294 COMPARE_OP              40 (==)
            298 POP_JUMP_IF_FALSE        1 (to 302)

 62         300 RETURN_CONST             5 ('Lens command delivered')

 63     >>  302 LOAD_FAST                0 (event)
            304 LOAD_ATTR                0 (event_type)
            324 LOAD_GLOBAL              2 (EventType)
            334 LOAD_ATTR               14 (DEVICE_CAPABILITY_MISSING)
            354 COMPARE_OP              40 (==)
            358 POP_JUMP_IF_FALSE        1 (to 362)

 64         360 RETURN_CONST             6 ('Device capability missing')

 65     >>  362 LOAD_FAST                0 (event)
            364 LOAD_ATTR                0 (event_type)
            384 LOAD_GLOBAL              2 (EventType)
            394 LOAD_ATTR               16 (DEVICE_DELIVERY_FAILED)
            414 COMPARE_OP              40 (==)
            418 POP_JUMP_IF_FALSE        1 (to 422)

 66         420 RETURN_CONST             7 ('Device delivery failed')

 67     >>  422 LOAD_FAST                0 (event)
            424 LOAD_ATTR                0 (event_type)
            444 LOAD_GLOBAL              2 (EventType)
            454 LOAD_ATTR               18 (JOB_STARTED)
            474 COMPARE_OP              40 (==)
            478 POP_JUMP_IF_FALSE        1 (to 482)

 68         480 RETURN_CONST             8 ('Document analysis job accepted')

 69     >>  482 LOAD_FAST                0 (event)
            484 LOAD_ATTR                0 (event_type)
            504 LOAD_GLOBAL              2 (EventType)
            514 LOAD_ATTR               20 (JOB_STATUS_UPDATED)
            534 COMPARE_OP              40 (==)
            538 POP_JUMP_IF_FALSE        1 (to 542)

 70         540 RETURN_CONST             9 ('Document analysis job updated')

 71     >>  542 LOAD_FAST                0 (event)
            544 LOAD_ATTR                0 (event_type)
            564 LOAD_GLOBAL              2 (EventType)
            574 LOAD_ATTR               22 (JOB_COMPLETED)
            594 COMPARE_OP              40 (==)
            598 POP_JUMP_IF_FALSE        1 (to 602)

 72         600 RETURN_CONST            10 ('Document analysis job completed')

 73     >>  602 LOAD_FAST                0 (event)
            604 LOAD_ATTR                0 (event_type)
            624 LOAD_GLOBAL              2 (EventType)
            634 LOAD_ATTR               24 (JOB_FAILED)
            654 COMPARE_OP              40 (==)
            658 POP_JUMP_IF_FALSE        1 (to 662)

 74         660 RETURN_CONST            11 ('Document analysis job failed')

 75     >>  662 LOAD_FAST                0 (event)
            664 LOAD_ATTR                0 (event_type)
            684 LOAD_GLOBAL              2 (EventType)
            694 LOAD_ATTR               26 (AI_CALL_FAILED)
            714 COMPARE_OP              40 (==)
            718 POP_JUMP_IF_FALSE        1 (to 722)

 76         720 RETURN_CONST            12 ('Document analysis attempt failed')

 77     >>  722 LOAD_FAST                0 (event)
            724 LOAD_ATTR                0 (event_type)
            744 LOAD_GLOBAL              2 (EventType)
            754 LOAD_ATTR               28 (ALERT_FEEDBACK_GIVEN)
            774 COMPARE_OP              40 (==)
            778 POP_JUMP_IF_FALSE        1 (to 782)

 78         780 RETURN_CONST            13 ('Lens feedback recorded')

 79     >>  782 LOAD_FAST                0 (event)
            784 LOAD_ATTR                0 (event_type)
            804 LOAD_ATTR               30 (value)
            824 LOAD_ATTR               33 (NULL|self + replace)
            844 LOAD_CONST              14 ('_')
            846 LOAD_CONST              15 (' ')
            848 CALL                     2
            856 LOAD_ATTR               35 (NULL|self + title)
            876 CALL                     0
            884 RETURN_VALUE

Disassembly of <code object build_trace_detail at 0x000001494120A320, file "C:\Users\renan\OneDrive\Documents\New Era Glasses\src\new_era\application\use_cases\get_session_trace.py", line 82>:
 82           0 RESUME                   0

 83           2 LOAD_FAST                0 (event)
              4 LOAD_ATTR                0 (metadata)
             24 STORE_FAST               1 (metadata)

 84          26 LOAD_FAST                0 (event)
             28 LOAD_ATTR                2 (event_type)
             48 LOAD_GLOBAL              4 (EventType)
             58 LOAD_ATTR                6 (OBSERVATION_CREATED)
             78 COMPARE_OP              40 (==)
             82 POP_JUMP_IF_FALSE       27 (to 138)

 85          84 LOAD_GLOBAL              9 (NULL + str)
             94 LOAD_FAST                1 (metadata)
             96 LOAD_ATTR               11 (NULL|self + get)
            116 LOAD_CONST               1 ('summary')
            118 LOAD_CONST               2 ('Observation received.')
            120 CALL                     2
            128 CALL                     1
            136 RETURN_VALUE

 86     >>  138 LOAD_FAST                0 (event)
            140 LOAD_ATTR                2 (event_type)
            160 LOAD_GLOBAL              4 (EventType)
            170 LOAD_ATTR               12 (ALERT_CANDIDATE_CREATED)
            190 COMPARE_OP              40 (==)
            194 POP_JUMP_IF_FALSE       87 (to 370)

 87         196 LOAD_GLOBAL              9 (NULL + str)
            206 LOAD_FAST                1 (metadata)
            208 LOAD_ATTR               11 (NULL|self + get)
            228 LOAD_CONST               3 ('priority')
            230 LOAD_CONST               4 ('unknown')
            232 CALL                     2
            240 CALL                     1
            248 LOAD_ATTR               15 (NULL|self + replace)
            268 LOAD_CONST               5 ('_')
            270 LOAD_CONST               6 (' ')
            272 CALL                     2
            280 STORE_FAST               2 (priority)

 88         282 LOAD_FAST                1 (metadata)
            284 LOAD_ATTR               11 (NULL|self + get)
            304 LOAD_CONST               7 ('confidence')
            306 CALL                     1
            314 STORE_FAST               3 (confidence)

 90         316 LOAD_FAST                1 (metadata)
            318 LOAD_ATTR               11 (NULL|self + get)
            338 LOAD_CONST               8 ('alert_type')
            340 LOAD_CONST               9 ('alert')
            342 CALL                     2
            350 FORMAT_VALUE             0
            352 LOAD_CONST              10 (' candidate with ')

 91         354 LOAD_FAST                2 (priority)
            356 FORMAT_VALUE             0
            358 LOAD_CONST              11 (' priority at confidence ')
            360 LOAD_FAST                3 (confidence)
            362 FORMAT_VALUE             0
            364 LOAD_CONST              12 ('.')

 90         366 BUILD_STRING             6

 89         368 RETURN_VALUE

 93     >>  370 LOAD_FAST                0 (event)
            372 LOAD_ATTR                2 (event_type)
            392 LOAD_GLOBAL              4 (EventType)
            402 LOAD_ATTR               16 (ALERT_SHOWN)
            422 LOAD_GLOBAL              4 (EventType)
            432 LOAD_ATTR               18 (ALERT_SUPPRESSED)
            452 BUILD_TUPLE              2
            454 CONTAINS_OP              0
            456 POP_JUMP_IF_FALSE       27 (to 512)

 94         458 LOAD_GLOBAL              9 (NULL + str)
            468 LOAD_FAST                1 (metadata)
            470 LOAD_ATTR               11 (NULL|self + get)
            490 LOAD_CONST              13 ('reason')
            492 LOAD_CONST              14 ('No decision reason recorded.')
            494 CALL                     2
            502 CALL                     1
            510 RETURN_VALUE

 95     >>  512 LOAD_FAST                0 (event)
            514 LOAD_ATTR                2 (event_type)
            534 LOAD_GLOBAL              4 (EventType)
            544 LOAD_ATTR               20 (LENS_COMMAND_DELIVERED)
            564 COMPARE_OP              40 (==)
            568 POP_JUMP_IF_FALSE       22 (to 614)

 96         570 LOAD_CONST              15 ('Rendered by ')
            572 LOAD_FAST                1 (metadata)
            574 LOAD_ATTR               11 (NULL|self + get)
            594 LOAD_CONST              16 ('adapter_name')
            596 LOAD_CONST              17 ('device adapter')
            598 CALL                     2
            606 FORMAT_VALUE             0
            608 LOAD_CONST              12 ('.')
            610 BUILD_STRING             3
            612 RETURN_VALUE

 97     >>  614 LOAD_FAST                0 (event)
            616 LOAD_ATTR                2 (event_type)
            636 LOAD_GLOBAL              4 (EventType)
            646 LOAD_ATTR               22 (DEVICE_CAPABILITY_MISSING)
            666 COMPARE_OP              40 (==)
            670 POP_JUMP_IF_FALSE       41 (to 754)

 99         672 LOAD_CONST              18 ('Missing ')
            674 LOAD_FAST                1 (metadata)
            676 LOAD_ATTR               11 (NULL|self + get)
            696 LOAD_CONST              19 ('missing_capability')
            698 LOAD_CONST              20 ('required capability')
            700 CALL                     2
            708 FORMAT_VALUE             0
            710 LOAD_CONST              21 (' on ')

100         712 LOAD_FAST                1 (metadata)
            714 LOAD_ATTR               11 (NULL|self + get)
            734 LOAD_CONST              16 ('adapter_name')
            736 LOAD_CONST              17 ('device adapter')
            738 CALL                     2
            746 FORMAT_VALUE             0
            748 LOAD_CONST              12 ('.')

 99         750 BUILD_STRING             5

 98         752 RETURN_VALUE

102     >>  754 LOAD_FAST                0 (event)
            756 LOAD_ATTR                2 (event_type)
            776 LOAD_GLOBAL              4 (EventType)
            786 LOAD_ATTR               24 (DEVICE_DELIVERY_FAILED)
            806 COMPARE_OP              40 (==)
            810 POP_JUMP_IF_FALSE       22 (to 856)

103         812 LOAD_CONST              22 ('Delivery failed on ')
            814 LOAD_FAST                1 (metadata)
            816 LOAD_ATTR               11 (NULL|self + get)
            836 LOAD_CONST              16 ('adapter_name')
            838 LOAD_CONST              17 ('device adapter')
            840 CALL                     2
            848 FORMAT_VALUE             0
            850 LOAD_CONST              12 ('.')
            852 BUILD_STRING             3
            854 RETURN_VALUE

104     >>  856 LOAD_FAST                0 (event)
            858 LOAD_ATTR                2 (event_type)
            878 LOAD_GLOBAL              4 (EventType)
            888 LOAD_ATTR               26 (JOB_STARTED)
            908 COMPARE_OP              40 (==)
            912 POP_JUMP_IF_FALSE       41 (to 996)

106         914 LOAD_CONST              23 ('Queued ')
            916 LOAD_FAST                1 (metadata)
            918 LOAD_ATTR               11 (NULL|self + get)
            938 LOAD_CONST              24 ('job_type')
            940 LOAD_CONST              25 ('job')
            942 CALL                     2
            950 FORMAT_VALUE             0
            952 LOAD_CONST              26 (' for ')

107         954 LOAD_FAST                1 (metadata)
            956 LOAD_ATTR               11 (NULL|self + get)
            976 LOAD_CONST              27 ('artifact_label')
            978 LOAD_CONST              28 ('document artifact')
            980 CALL                     2
            988 FORMAT_VALUE             0
            990 LOAD_CONST              12 ('.')

106         992 BUILD_STRING             5

105         994 RETURN_VALUE

109     >>  996 LOAD_FAST                0 (event)
            998 LOAD_ATTR                2 (event_type)
           1018 LOAD_GLOBAL              4 (EventType)
           1028 LOAD_ATTR               28 (JOB_STATUS_UPDATED)
           1048 COMPARE_OP              40 (==)
           1052 POP_JUMP_IF_FALSE       41 (to 1136)

111        1054 LOAD_CONST              29 ('Moved job from ')
           1056 LOAD_FAST                1 (metadata)
           1058 LOAD_ATTR               11 (NULL|self + get)
           1078 LOAD_CONST              30 ('from_status')
           1080 LOAD_CONST               4 ('unknown')
           1082 CALL                     2
           1090 FORMAT_VALUE             0
           1092 LOAD_CONST              31 (' to ')

112        1094 LOAD_FAST                1 (metadata)
           1096 LOAD_ATTR               11 (NULL|self + get)
           1116 LOAD_CONST              32 ('to_status')
           1118 LOAD_CONST               4 ('unknown')
           1120 CALL                     2
           1128 FORMAT_VALUE             0
           1130 LOAD_CONST              12 ('.')

111        1132 BUILD_STRING             5

110        1134 RETURN_VALUE

114     >> 1136 LOAD_FAST                0 (event)
           1138 LOAD_ATTR                2 (event_type)
           1158 LOAD_GLOBAL              4 (EventType)
           1168 LOAD_ATTR               30 (JOB_COMPLETED)
           1188 COMPARE_OP              40 (==)
           1192 POP_JUMP_IF_FALSE       22 (to 1238)

115        1194 LOAD_CONST              33 ('Completed ')
           1196 LOAD_FAST                1 (metadata)
           1198 LOAD_ATTR               11 (NULL|self + get)
           1218 LOAD_CONST              24 ('job_type')
           1220 LOAD_CONST              25 ('job')
           1222 CALL                     2
           1230 FORMAT_VALUE             0
           1232 LOAD_CONST              12 ('.')
           1234 BUILD_STRING             3
           1236 RETURN_VALUE

116     >> 1238 LOAD_FAST                0 (event)
           1240 LOAD_ATTR                2 (event_type)
           1260 LOAD_GLOBAL              4 (EventType)
           1270 LOAD_ATTR               32 (JOB_FAILED)
           1290 COMPARE_OP              40 (==)
           1294 POP_JUMP_IF_FALSE       22 (to 1340)

117        1296 LOAD_CONST              34 ('Failed ')
           1298 LOAD_FAST                1 (metadata)
           1300 LOAD_ATTR               11 (NULL|self + get)
           1320 LOAD_CONST              24 ('job_type')
           1322 LOAD_CONST              25 ('job')
           1324 CALL                     2
           1332 FORMAT_VALUE             0
           1334 LOAD_CONST              12 ('.')
           1336 BUILD_STRING             3
           1338 RETURN_VALUE

118     >> 1340 LOAD_FAST                0 (event)
           1342 LOAD_ATTR                2 (event_type)
           1362 LOAD_GLOBAL              4 (EventType)
           1372 LOAD_ATTR               34 (AI_CALL_FAILED)
           1392 COMPARE_OP              40 (==)
           1396 POP_JUMP_IF_FALSE       46 (to 1490)

119        1398 LOAD_FAST                1 (metadata)
           1400 LOAD_ATTR               11 (NULL|self + get)
           1420 LOAD_CONST              35 ('retry_scheduled')
           1422 CALL                     1
           1430 POP_JUMP_IF_FALSE        2 (to 1436)
           1432 LOAD_CONST              36 ('retry scheduled')
           1434 JUMP_FORWARD             1 (to 1438)
        >> 1436 LOAD_CONST              37 ('no retry')
        >> 1438 STORE_FAST               4 (retry_text)

120        1440 LOAD_CONST              38 ('Attempt ')
           1442 LOAD_FAST                1 (metadata)
           1444 LOAD_ATTR               11 (NULL|self + get)
           1464 LOAD_CONST              39 ('attempt')
           1466 LOAD_CONST               4 ('unknown')
           1468 CALL                     2
           1476 FORMAT_VALUE             0
           1478 LOAD_CONST              40 (' failed; ')
           1480 LOAD_FAST                4 (retry_text)
           1482 FORMAT_VALUE             0
           1484 LOAD_CONST              12 ('.')
           1486 BUILD_STRING             5
           1488 RETURN_VALUE

121     >> 1490 LOAD_FAST                0 (event)
           1492 LOAD_ATTR                2 (event_type)
           1512 LOAD_GLOBAL              4 (EventType)
           1522 LOAD_ATTR               36 (ALERT_FEEDBACK_GIVEN)
           1542 COMPARE_OP              40 (==)
           1546 POP_JUMP_IF_FALSE       49 (to 1646)

122        1548 LOAD_GLOBAL              9 (NULL + str)
           1558 LOAD_FAST                1 (metadata)
           1560 LOAD_ATTR               11 (NULL|self + get)
           1580 LOAD_CONST              41 ('feedback')
           1582 LOAD_CONST              41 ('feedback')
           1584 CALL                     2
           1592 CALL                     1
           1600 LOAD_ATTR               15 (NULL|self + replace)
           1620 LOAD_CONST               5 ('_')
           1622 LOAD_CONST               6 (' ')
           1624 CALL                     2
           1632 STORE_FAST               5 (feedback)

123        1634 LOAD_CONST              42 ('Marked the lens alert as ')
           1636 LOAD_FAST                5 (feedback)
           1638 FORMAT_VALUE             0
           1640 LOAD_CONST              12 ('.')
           1642 BUILD_STRING             3
           1644 RETURN_VALUE

124     >> 1646 RETURN_CONST            43 ('Event recorded.')

Disassembly of <code object build_trace_step at 0x000001494126DD20, file "C:\Users\renan\OneDrive\Documents\New Era Glasses\src\new_era\application\use_cases\get_session_trace.py", line 127>:
127           0 RESUME                   0

128           2 LOAD_FAST                0 (event_type)
              4 LOAD_GLOBAL              0 (EventType)
             14 LOAD_ATTR                2 (OBSERVATION_CREATED)
             34 COMPARE_OP              40 (==)
             38 POP_JUMP_IF_FALSE        1 (to 42)

129          40 RETURN_CONST             1 ('observation')

130     >>   42 LOAD_FAST                0 (event_type)
             44 LOAD_GLOBAL              0 (EventType)
             54 LOAD_ATTR                4 (ALERT_CANDIDATE_CREATED)
             74 COMPARE_OP              40 (==)
             78 POP_JUMP_IF_FALSE        1 (to 82)

131          80 RETURN_CONST             2 ('candidate')

132     >>   82 LOAD_FAST                0 (event_type)
             84 LOAD_GLOBAL              0 (EventType)
             94 LOAD_ATTR                6 (ALERT_SHOWN)
            114 LOAD_GLOBAL              0 (EventType)
            124 LOAD_ATTR                8 (ALERT_SUPPRESSED)
            144 BUILD_TUPLE              2
            146 CONTAINS_OP              0
            148 POP_JUMP_IF_FALSE        1 (to 152)

133         150 RETURN_CONST             3 ('decision')

134     >>  152 LOAD_FAST                0 (event_type)

135         154 LOAD_GLOBAL              0 (EventType)
            164 LOAD_ATTR               10 (LENS_COMMAND_DELIVERED)

136         184 LOAD_GLOBAL              0 (EventType)
            194 LOAD_ATTR               12 (DEVICE_CAPABILITY_MISSING)

137         214 LOAD_GLOBAL              0 (EventType)
            224 LOAD_ATTR               14 (DEVICE_DELIVERY_FAILED)

134         244 BUILD_TUPLE              3
            246 CONTAINS_OP              0
            248 POP_JUMP_IF_FALSE        1 (to 252)

139         250 RETURN_CONST             4 ('delivery')

140     >>  252 LOAD_FAST                0 (event_type)

141         254 LOAD_GLOBAL              0 (EventType)
            264 LOAD_ATTR               16 (JOB_STARTED)

142         284 LOAD_GLOBAL              0 (EventType)
            294 LOAD_ATTR               18 (JOB_STATUS_UPDATED)

143         314 LOAD_GLOBAL              0 (EventType)
            324 LOAD_ATTR               20 (JOB_COMPLETED)

144         344 LOAD_GLOBAL              0 (EventType)
            354 LOAD_ATTR               22 (JOB_FAILED)

140         374 BUILD_TUPLE              4
            376 CONTAINS_OP              0
            378 POP_JUMP_IF_FALSE        1 (to 382)

146         380 RETURN_CONST             5 ('job')

147     >>  382 LOAD_FAST                0 (event_type)
            384 LOAD_GLOBAL              0 (EventType)
            394 LOAD_ATTR               24 (AI_CALL_FAILED)
            414 COMPARE_OP              40 (==)
            418 POP_JUMP_IF_FALSE        1 (to 422)

148         420 RETURN_CONST             6 ('provider')

149     >>  422 LOAD_FAST                0 (event_type)
            424 LOAD_GLOBAL              0 (EventType)
            434 LOAD_ATTR               26 (ALERT_FEEDBACK_GIVEN)
            454 COMPARE_OP              40 (==)
            458 POP_JUMP_IF_FALSE        1 (to 462)

150         460 RETURN_CONST             7 ('feedback')

151     >>  462 RETURN_CONST             8 ('system')

Disassembly of <code object normalize_trace_limit at 0x000001494112D110, file "C:\Users\renan\OneDrive\Documents\New Era Glasses\src\new_era\application\use_cases\get_session_trace.py", line 174>:
174           0 RESUME                   0

175           2 LOAD_FAST                0 (limit)
              4 POP_JUMP_IF_NOT_NONE     6 (to 18)

176           6 LOAD_GLOBAL              0 (DEFAULT_TRACE_LIMIT)
             16 RETURN_VALUE

177     >>   18 LOAD_FAST                0 (limit)
             20 LOAD_CONST               1 (1)
             22 COMPARE_OP               2 (<)
             26 POP_JUMP_IF_FALSE       11 (to 50)

178          28 LOAD_GLOBAL              3 (NULL + ValueError)
             38 LOAD_CONST               2 ('limit must be at least 1')
             40 CALL                     1
             48 RAISE_VARARGS            1

179     >>   50 LOAD_GLOBAL              5 (NULL + min)
             60 LOAD_FAST                0 (limit)
             62 LOAD_GLOBAL              6 (MAX_TRACE_LIMIT)
             72 CALL                     2
             80 RETURN_VALUE

Disassembly of <code object encode_trace_cursor at 0x0000014941079A10, file "C:\Users\renan\OneDrive\Documents\New Era Glasses\src\new_era\application\use_cases\get_session_trace.py", line 182>:
182           0 RESUME                   0

183           2 LOAD_FAST                0 (event)
              4 LOAD_ATTR                0 (created_at)
             24 LOAD_ATTR                3 (NULL|self + isoformat)
             44 CALL                     0
             52 FORMAT_VALUE             0
             54 LOAD_CONST               1 ('|')
             56 LOAD_FAST                0 (event)
             58 LOAD_ATTR                4 (event_id)
             78 FORMAT_VALUE             0
             80 BUILD_STRING             3
             82 STORE_FAST               1 (value)

184          84 LOAD_GLOBAL              7 (NULL + urlsafe_b64encode)
             94 LOAD_FAST                1 (value)
             96 LOAD_ATTR                9 (NULL|self + encode)
            116 LOAD_CONST               2 ('utf-8')
            118 CALL                     1
            126 CALL                     1
            134 LOAD_ATTR               11 (NULL|self + decode)
            154 LOAD_CONST               3 ('ascii')
            156 CALL                     1
            164 RETURN_VALUE

Disassembly of <code object decode_trace_cursor at 0x0000014940CCE3A0, file "C:\Users\renan\OneDrive\Documents\New Era Glasses\src\new_era\application\use_cases\get_session_trace.py", line 187>:
187           0 RESUME                   0

188           2 LOAD_FAST                0 (cursor)
              4 POP_JUMP_IF_NOT_NONE     1 (to 8)

189           6 RETURN_CONST             0 (None)

190     >>    8 NOP

191          10 LOAD_GLOBAL              1 (NULL + urlsafe_b64decode)
             20 LOAD_FAST                0 (cursor)
             22 LOAD_ATTR                3 (NULL|self + encode)
             42 LOAD_CONST               1 ('ascii')
             44 CALL                     1
             52 CALL                     1
             60 LOAD_ATTR                5 (NULL|self + decode)
             80 LOAD_CONST               2 ('utf-8')
             82 CALL                     1
             90 STORE_FAST               1 (decoded)

192          92 LOAD_FAST                1 (decoded)
             94 LOAD_ATTR                7 (NULL|self + split)
            114 LOAD_CONST               3 ('|')
            116 LOAD_CONST               4 (1)
            118 CALL                     2
            126 UNPACK_SEQUENCE          2
            130 STORE_FAST               2 (created_at_text)
            132 STORE_FAST               3 (event_id)

193         134 LOAD_GLOBAL              9 (NULL + datetime)
            144 LOAD_ATTR               10 (fromisoformat)
            164 LOAD_FAST                2 (created_at_text)
            166 CALL                     1
            174 LOAD_FAST                3 (event_id)
            176 BUILD_TUPLE              2
            178 RETURN_VALUE
        >>  180 PUSH_EXC_INFO

194         182 LOAD_GLOBAL             12 (Exception)
            192 CHECK_EXC_MATCH
            194 POP_JUMP_IF_FALSE       17 (to 230)
            196 STORE_FAST               4 (exc)

195         198 LOAD_GLOBAL             15 (NULL + ValueError)
            208 LOAD_CONST               5 ('invalid trace cursor')
            210 CALL                     1
            218 LOAD_FAST                4 (exc)
            220 RAISE_VARARGS            2
        >>  222 LOAD_CONST               0 (None)
            224 STORE_FAST               4 (exc)
            226 DELETE_FAST              4 (exc)
            228 RERAISE                  1

194     >>  230 RERAISE                  0
        >>  232 COPY                     3
            234 POP_EXCEPT
            236 RERAISE                  1
ExceptionTable:
  10 to 176 -> 180 [0]
  180 to 196 -> 232 [1] lasti
  198 to 220 -> 222 [1] lasti
  222 to 230 -> 232 [1] lasti

Disassembly of <code object event_types_for_steps at 0x0000014941124030, file "C:\Users\renan\OneDrive\Documents\New Era Glasses\src\new_era\application\use_cases\get_session_trace.py", line 198>:
198           0 RESUME                   0

199           2 LOAD_FAST                0 (steps)
              4 POP_JUMP_IF_TRUE         1 (to 8)

200           6 RETURN_CONST             0 (None)

201     >>    8 LOAD_FAST                0 (steps)
             10 LOAD_ATTR                1 (NULL|self + difference)
             30 LOAD_GLOBAL              2 (TRACE_STEP_EVENT_TYPES)
             40 LOAD_ATTR                5 (NULL|self + keys)
             60 CALL                     0
             68 CALL                     1
             76 STORE_FAST               1 (unknown_steps)

202          78 LOAD_FAST                1 (unknown_steps)
             80 POP_JUMP_IF_FALSE       40 (to 162)

203          82 LOAD_CONST               1 (', ')
             84 LOAD_ATTR                7 (NULL|self + join)
            104 LOAD_GLOBAL              9 (NULL + sorted)
            114 LOAD_FAST                1 (unknown_steps)
            116 CALL                     1
            124 CALL                     1
            132 STORE_FAST               2 (names)

204         134 LOAD_GLOBAL             11 (NULL + ValueError)
            144 LOAD_CONST               2 ('unknown trace step filter: ')
            146 LOAD_FAST                2 (names)
            148 FORMAT_VALUE             0
            150 BUILD_STRING             2
            152 CALL                     1
            160 RAISE_VARARGS            1

206     >>  162 LOAD_GLOBAL             13 (NULL + set)
            172 CALL                     0
            180 STORE_FAST               3 (event_types)

207         182 LOAD_FAST                0 (steps)
            184 GET_ITER
        >>  186 FOR_ITER                26 (to 242)
            190 STORE_FAST               4 (step)

208         192 LOAD_FAST                3 (event_types)
            194 LOAD_ATTR               15 (NULL|self + update)
            214 LOAD_GLOBAL              2 (TRACE_STEP_EVENT_TYPES)
            224 LOAD_FAST                4 (step)
            226 BINARY_SUBSCR
            230 CALL                     1
            238 POP_TOP
            240 JUMP_BACKWARD           28 (to 186)

207     >>  242 END_FOR

209         244 LOAD_FAST                3 (event_types)
            246 RETURN_VALUE

Disassembly of <code object combine_event_type_filters at 0x0000014941148470, file "C:\Users\renan\OneDrive\Documents\New Era Glasses\src\new_era\application\use_cases\get_session_trace.py", line 212>:
212           0 RESUME                   0

217           2 LOAD_GLOBAL              1 (NULL + event_types_for_steps)
             12 LOAD_FAST                1 (steps)
             14 CALL                     1
             22 STORE_FAST               2 (step_event_types)

218          24 LOAD_FAST                0 (event_types)
             26 POP_JUMP_IF_NOT_NONE     2 (to 32)

219          28 LOAD_FAST                2 (step_event_types)
             30 RETURN_VALUE

220     >>   32 LOAD_FAST                2 (step_event_types)
             34 POP_JUMP_IF_NOT_NONE     2 (to 40)

221          36 LOAD_FAST                0 (event_types)
             38 RETURN_VALUE

222     >>   40 LOAD_FAST                0 (event_types)
             42 LOAD_ATTR                3 (NULL|self + intersection)
             62 LOAD_FAST                2 (step_event_types)
             64 CALL                     1
             72 RETURN_VALUE

Disassembly of <code object GetSessionTrace at 0x000001494112D470, file "C:\Users\renan\OneDrive\Documents\New Era Glasses\src\new_era\application\use_cases\get_session_trace.py", line 225>:
225           0 RESUME                   0
              2 LOAD_NAME                0 (__name__)
              4 STORE_NAME               1 (__module__)
              6 LOAD_CONST               0 ('GetSessionTrace')
              8 STORE_NAME               2 (__qualname__)
             10 SETUP_ANNOTATIONS

227          12 LOAD_CONST               1 ('EventStore')
             14 LOAD_NAME                3 (__annotations__)
             16 LOAD_CONST               2 ('event_store')
             18 STORE_SUBSCR

233          22 LOAD_CONST               3 (None)

234          24 LOAD_CONST               3 (None)

235          26 LOAD_CONST               3 (None)

236          28 LOAD_CONST               3 (None)

237          30 LOAD_CONST               3 (None)

238          32 LOAD_CONST               3 (None)

239          34 LOAD_CONST               3 (None)

240          36 LOAD_CONST               3 (None)

241          38 LOAD_CONST               3 (None)

229          40 LOAD_CONST               4 (('user_id', 'trace_id', 'module', 'event_types', 'steps', 'created_after', 'created_before', 'limit', 'cursor'))
             42 BUILD_CONST_KEY_MAP      9

232          44 NOP

229          46 NOP

233          48 NOP

229          50 NOP

234          52 NOP

229          54 NOP

235          56 NOP

229          58 NOP

236          60 NOP

229          62 NOP

237          64 NOP

229          66 NOP

238          68 NOP

229          70 NOP

239          72 NOP

229          74 NOP

240          76 NOP

229          78 NOP

241          80 NOP

229          82 NOP

242          84 NOP

229          86 LOAD_CONST               6 (('session_id', 'str', 'user_id', 'str | None', 'trace_id', 'str | None', 'module', 'str | None', 'event_types', 'set[EventType] | None', 'steps', 'set[str] | None', 'created_after', 'datetime | None', 'created_before', 'datetime | None', 'limit', 'int | None', 'cursor', 'str | None', 'return', 'SessionTraceReadModel'))
             88 LOAD_CONST               5 (<code object execute at 0x0000014940FFDE30, file "C:\Users\renan\OneDrive\Documents\New Era Glasses\src\new_era\application\use_cases\get_session_trace.py", line 229>)
             90 MAKE_FUNCTION            6 (kwdefaults, annotations)
             92 STORE_NAME               4 (execute)
             94 RETURN_CONST             3 (None)

Disassembly of <code object execute at 0x0000014940FFDE30, file "C:\Users\renan\OneDrive\Documents\New Era Glasses\src\new_era\application\use_cases\get_session_trace.py", line 229>:
229           0 RESUME                   0

243           2 LOAD_GLOBAL              1 (NULL + normalize_trace_limit)
             12 LOAD_FAST                9 (limit)
             14 CALL                     1
             22 STORE_FAST              11 (normalized_limit)

244          24 LOAD_GLOBAL              3 (NULL + combine_event_type_filters)

245          34 LOAD_FAST                5 (event_types)

246          36 LOAD_FAST                6 (steps)

244          38 KW_NAMES                 1 (('event_types', 'steps'))
             40 CALL                     2
             48 STORE_FAST              12 (combined_event_types)

248          50 LOAD_FAST                0 (self)
             52 LOAD_ATTR                4 (event_store)
             72 LOAD_ATTR                7 (NULL|self + list_events)

249          92 LOAD_FAST                2 (user_id)

250          94 LOAD_FAST                1 (session_id)

251          96 LOAD_FAST                3 (trace_id)

252          98 LOAD_FAST                4 (module)

253         100 LOAD_FAST               12 (combined_event_types)

254         102 LOAD_FAST                7 (created_after)

255         104 LOAD_FAST                8 (created_before)

256         106 LOAD_GLOBAL              9 (NULL + decode_trace_cursor)
            116 LOAD_FAST               10 (cursor)
            118 CALL                     1

257         126 LOAD_FAST               11 (normalized_limit)
            128 LOAD_CONST               2 (1)
            130 BINARY_OP                0 (+)

248         134 KW_NAMES                 3 (('user_id', 'session_id', 'trace_id', 'module', 'event_types', 'created_after', 'created_before', 'after', 'limit'))
            136 CALL                     9
            144 STORE_FAST              13 (events)

259         146 LOAD_GLOBAL             11 (NULL + len)
            156 LOAD_FAST               13 (events)
            158 CALL                     1
            166 LOAD_FAST               11 (normalized_limit)
            168 COMPARE_OP              68 (>)
            172 STORE_FAST              14 (has_more)

260         174 LOAD_FAST               13 (events)
            176 LOAD_CONST               0 (None)
            178 LOAD_FAST               11 (normalized_limit)
            180 BINARY_SLICE
            182 STORE_FAST              15 (page_events)

261         184 LOAD_GLOBAL             13 (NULL + tuple)
            194 LOAD_CONST               4 (<code object <genexpr> at 0x0000014941124570, file "C:\Users\renan\OneDrive\Documents\New Era Glasses\src\new_era\application\use_cases\get_session_trace.py", line 261>)
            196 MAKE_FUNCTION            0

270         198 LOAD_FAST               15 (page_events)
            200 GET_ITER

261         202 CALL                     0
            210 CALL                     1
            218 STORE_FAST              16 (entries)

272         220 LOAD_GLOBAL             15 (NULL + SessionTraceReadModel)

273         230 LOAD_FAST                1 (session_id)

274         232 LOAD_FAST                3 (trace_id)

275         234 LOAD_GLOBAL             11 (NULL + len)
            244 LOAD_FAST               16 (entries)
            246 CALL                     1

277         254 LOAD_FAST               14 (has_more)
            256 POP_JUMP_IF_FALSE       22 (to 302)
            258 LOAD_FAST               15 (page_events)
            260 POP_JUMP_IF_FALSE       20 (to 302)

276         262 LOAD_GLOBAL             17 (NULL + encode_trace_cursor)
            272 LOAD_FAST               15 (page_events)
            274 LOAD_CONST               5 (-1)
            276 BINARY_SUBSCR
            280 CALL                     1

279         288 LOAD_FAST               16 (entries)

272         290 KW_NAMES                 6 (('session_id', 'trace_id', 'event_count', 'next_cursor', 'session_trace'))
            292 CALL                     5
            300 RETURN_VALUE

278     >>  302 LOAD_CONST               0 (None)

279         304 LOAD_FAST               16 (entries)

272         306 KW_NAMES                 6 (('session_id', 'trace_id', 'event_count', 'next_cursor', 'session_trace'))
            308 CALL                     5
            316 RETURN_VALUE

Disassembly of <code object <genexpr> at 0x0000014941124570, file "C:\Users\renan\OneDrive\Documents\New Era Glasses\src\new_era\application\use_cases\get_session_trace.py", line 261>:
261           0 RETURN_GENERATOR
              2 POP_TOP
              4 RESUME                   0
              6 LOAD_FAST                0 (.0)

270     >>    8 FOR_ITER               112 (to 236)
             12 STORE_FAST               1 (event)

262          14 LOAD_GLOBAL              1 (NULL + SessionTraceEntry)

263          24 LOAD_FAST                1 (event)
             26 LOAD_ATTR                2 (event_id)

264          46 LOAD_FAST                1 (event)
             48 LOAD_ATTR                4 (event_type)
             68 LOAD_ATTR                6 (value)

265          88 LOAD_GLOBAL              9 (NULL + build_trace_step)
             98 LOAD_FAST                1 (event)
            100 LOAD_ATTR                4 (event_type)
            120 CALL                     1

266         128 LOAD_GLOBAL             11 (NULL + build_trace_title)
            138 LOAD_FAST                1 (event)
            140 CALL                     1

267         148 LOAD_GLOBAL             13 (NULL + build_trace_detail)
            158 LOAD_FAST                1 (event)
            160 CALL                     1

268         168 LOAD_FAST                1 (event)
            170 LOAD_ATTR               14 (created_at)
            190 LOAD_ATTR               17 (NULL|self + isoformat)
            210 CALL                     0

262         218 KW_NAMES                 0 (('event_id', 'event_type', 'step', 'title', 'detail', 'created_at'))
            220 CALL                     6
            228 YIELD_VALUE              1
            230 RESUME                   1
            232 POP_TOP
            234 JUMP_BACKWARD          114 (to 8)

270     >>  236 END_FOR
            238 RETURN_CONST             1 (None)
        >>  240 CALL_INTRINSIC_1         3 (INTRINSIC_STOPITERATION_ERROR)
            242 RERAISE                  1
ExceptionTable:
  4 to 238 -> 240 [0] lasti

  ## code_object: SessionTraceEntry
  filename: C:\Users\renan\OneDrive\Documents\New Era Glasses\src\new_era\application\use_cases\get_session_trace.py
  first_line: 14
  argcount: 0
  locals: 0
  stacksize: 3
  flags: 16777216
  names: ['__name__', '__module__', '__qualname__', '__annotations__', 'to_dict']
  varnames: []
  cellvars: []
  freevars: []
  disassembly:
   14           0 RESUME                   0
                2 LOAD_NAME                0 (__name__)
                4 STORE_NAME               1 (__module__)
                6 LOAD_CONST               0 ('SessionTraceEntry')
                8 STORE_NAME               2 (__qualname__)
               10 SETUP_ANNOTATIONS
  
   16          12 LOAD_CONST               1 ('str')
               14 LOAD_NAME                3 (__annotations__)
               16 LOAD_CONST               2 ('event_id')
               18 STORE_SUBSCR
  
   17          22 LOAD_CONST               1 ('str')
               24 LOAD_NAME                3 (__annotations__)
               26 LOAD_CONST               3 ('event_type')
               28 STORE_SUBSCR
  
   18          32 LOAD_CONST               1 ('str')
               34 LOAD_NAME                3 (__annotations__)
               36 LOAD_CONST               4 ('step')
               38 STORE_SUBSCR
  
   19          42 LOAD_CONST               1 ('str')
               44 LOAD_NAME                3 (__annotations__)
               46 LOAD_CONST               5 ('title')
               48 STORE_SUBSCR
  
   20          52 LOAD_CONST               1 ('str')
               54 LOAD_NAME                3 (__annotations__)
               56 LOAD_CONST               6 ('detail')
               58 STORE_SUBSCR
  
   21          62 LOAD_CONST               1 ('str')
               64 LOAD_NAME                3 (__annotations__)
               66 LOAD_CONST               7 ('created_at')
               68 STORE_SUBSCR
  
   23          72 LOAD_CONST              10 (('return', 'dict[str, object]'))
               74 LOAD_CONST               8 (<code object to_dict at 0x000001494104E790, file "C:\Users\renan\OneDrive\Documents\New Era Glasses\src\new_era\application\use_cases\get_session_trace.py", line 23>)
               76 MAKE_FUNCTION            4 (annotations)
               78 STORE_NAME               4 (to_dict)
               80 RETURN_CONST             9 (None)
  
  Disassembly of <code object to_dict at 0x000001494104E790, file "C:\Users\renan\OneDrive\Documents\New Era Glasses\src\new_era\application\use_cases\get_session_trace.py", line 23>:
   23           0 RESUME                   0
  
   25           2 LOAD_FAST                0 (self)
                4 LOAD_ATTR                0 (event_id)
  
   26          24 LOAD_FAST                0 (self)
               26 LOAD_ATTR                2 (event_type)
  
   27          46 LOAD_FAST                0 (self)
               48 LOAD_ATTR                4 (step)
  
   28          68 LOAD_FAST                0 (self)
               70 LOAD_ATTR                6 (title)
  
   29          90 LOAD_FAST                0 (self)
               92 LOAD_ATTR                8 (detail)
  
   30         112 LOAD_FAST                0 (self)
              114 LOAD_ATTR               10 (created_at)
  
   24         134 LOAD_CONST               1 (('event_id', 'event_type', 'step', 'title', 'detail', 'created_at'))
              136 BUILD_CONST_KEY_MAP      6
              138 RETURN_VALUE

    ## code_object: to_dict
    filename: C:\Users\renan\OneDrive\Documents\New Era Glasses\src\new_era\application\use_cases\get_session_trace.py
    first_line: 23
    argcount: 1
    locals: 1
    stacksize: 7
    flags: 16777219
    names: ['event_id', 'event_type', 'step', 'title', 'detail', 'created_at']
    varnames: ['self']
    cellvars: []
    freevars: []
    disassembly:
     23           0 RESUME                   0
    
     25           2 LOAD_FAST                0 (self)
                  4 LOAD_ATTR                0 (event_id)
    
     26          24 LOAD_FAST                0 (self)
                 26 LOAD_ATTR                2 (event_type)
    
     27          46 LOAD_FAST                0 (self)
                 48 LOAD_ATTR                4 (step)
    
     28          68 LOAD_FAST                0 (self)
                 70 LOAD_ATTR                6 (title)
    
     29          90 LOAD_FAST                0 (self)
                 92 LOAD_ATTR                8 (detail)
    
     30         112 LOAD_FAST                0 (self)
                114 LOAD_ATTR               10 (created_at)
    
     24         134 LOAD_CONST               1 (('event_id', 'event_type', 'step', 'title', 'detail', 'created_at'))
                136 BUILD_CONST_KEY_MAP      6
                138 RETURN_VALUE

  ## code_object: SessionTraceReadModel
  filename: C:\Users\renan\OneDrive\Documents\New Era Glasses\src\new_era\application\use_cases\get_session_trace.py
  first_line: 34
  argcount: 0
  locals: 0
  stacksize: 3
  flags: 16777216
  names: ['__name__', '__module__', '__qualname__', '__annotations__', 'to_dict']
  varnames: []
  cellvars: []
  freevars: []
  disassembly:
   34           0 RESUME                   0
                2 LOAD_NAME                0 (__name__)
                4 STORE_NAME               1 (__module__)
                6 LOAD_CONST               0 ('SessionTraceReadModel')
                8 STORE_NAME               2 (__qualname__)
               10 SETUP_ANNOTATIONS
  
   36          12 LOAD_CONST               1 ('str')
               14 LOAD_NAME                3 (__annotations__)
               16 LOAD_CONST               2 ('session_id')
               18 STORE_SUBSCR
  
   37          22 LOAD_CONST               3 ('str | None')
               24 LOAD_NAME                3 (__annotations__)
               26 LOAD_CONST               4 ('trace_id')
               28 STORE_SUBSCR
  
   38          32 LOAD_CONST               5 ('int')
               34 LOAD_NAME                3 (__annotations__)
               36 LOAD_CONST               6 ('event_count')
               38 STORE_SUBSCR
  
   39          42 LOAD_CONST               3 ('str | None')
               44 LOAD_NAME                3 (__annotations__)
               46 LOAD_CONST               7 ('next_cursor')
               48 STORE_SUBSCR
  
   40          52 LOAD_CONST               8 ('tuple[SessionTraceEntry, ...]')
               54 LOAD_NAME                3 (__annotations__)
               56 LOAD_CONST               9 ('session_trace')
               58 STORE_SUBSCR
  
   42          62 LOAD_CONST              12 (('return', 'dict[str, object]'))
               64 LOAD_CONST              10 (<code object to_dict at 0x00000149411381B0, file "C:\Users\renan\OneDrive\Documents\New Era Glasses\src\new_era\application\use_cases\get_session_trace.py", line 42>)
               66 MAKE_FUNCTION            4 (annotations)
               68 STORE_NAME               4 (to_dict)
               70 RETURN_CONST            11 (None)
  
  Disassembly of <code object to_dict at 0x00000149411381B0, file "C:\Users\renan\OneDrive\Documents\New Era Glasses\src\new_era\application\use_cases\get_session_trace.py", line 42>:
   42           0 RESUME                   0
  
   44           2 LOAD_FAST                0 (self)
                4 LOAD_ATTR                0 (session_id)
  
   45          24 LOAD_FAST                0 (self)
               26 LOAD_ATTR                2 (trace_id)
  
   46          46 LOAD_FAST                0 (self)
               48 LOAD_ATTR                4 (event_count)
  
   47          68 LOAD_FAST                0 (self)
               70 LOAD_ATTR                6 (next_cursor)
  
   48          90 LOAD_FAST                0 (self)
               92 LOAD_ATTR                8 (session_trace)
              112 GET_ITER
              114 LOAD_FAST_AND_CLEAR      1 (entry)
              116 SWAP                     2
              118 BUILD_LIST               0
              120 SWAP                     2
          >>  122 FOR_ITER                18 (to 162)
              126 STORE_FAST               1 (entry)
              128 LOAD_FAST                1 (entry)
              130 LOAD_ATTR               11 (NULL|self + to_dict)
              150 CALL                     0
              158 LIST_APPEND              2
              160 JUMP_BACKWARD           20 (to 122)
          >>  162 END_FOR
              164 SWAP                     2
              166 STORE_FAST               1 (entry)
  
   43         168 LOAD_CONST               1 (('session_id', 'trace_id', 'event_count', 'next_cursor', 'session_trace'))
              170 BUILD_CONST_KEY_MAP      5
              172 RETURN_VALUE
          >>  174 SWAP                     2
              176 POP_TOP
  
   48         178 SWAP                     2
              180 STORE_FAST               1 (entry)
              182 RERAISE                  0
  ExceptionTable:
    118 to 162 -> 174 [6]

    ## code_object: to_dict
    filename: C:\Users\renan\OneDrive\Documents\New Era Glasses\src\new_era\application\use_cases\get_session_trace.py
    first_line: 42
    argcount: 1
    locals: 2
    stacksize: 9
    flags: 16777219
    names: ['session_id', 'trace_id', 'event_count', 'next_cursor', 'session_trace', 'to_dict']
    varnames: ['self', 'entry']
    cellvars: []
    freevars: []
    disassembly:
     42           0 RESUME                   0
    
     44           2 LOAD_FAST                0 (self)
                  4 LOAD_ATTR                0 (session_id)
    
     45          24 LOAD_FAST                0 (self)
                 26 LOAD_ATTR                2 (trace_id)
    
     46          46 LOAD_FAST                0 (self)
                 48 LOAD_ATTR                4 (event_count)
    
     47          68 LOAD_FAST                0 (self)
                 70 LOAD_ATTR                6 (next_cursor)
    
     48          90 LOAD_FAST                0 (self)
                 92 LOAD_ATTR                8 (session_trace)
                112 GET_ITER
                114 LOAD_FAST_AND_CLEAR      1 (entry)
                116 SWAP                     2
                118 BUILD_LIST               0
                120 SWAP                     2
            >>  122 FOR_ITER                18 (to 162)
                126 STORE_FAST               1 (entry)
                128 LOAD_FAST                1 (entry)
                130 LOAD_ATTR               11 (NULL|self + to_dict)
                150 CALL                     0
                158 LIST_APPEND              2
                160 JUMP_BACKWARD           20 (to 122)
            >>  162 END_FOR
                164 SWAP                     2
                166 STORE_FAST               1 (entry)
    
     43         168 LOAD_CONST               1 (('session_id', 'trace_id', 'event_count', 'next_cursor', 'session_trace'))
                170 BUILD_CONST_KEY_MAP      5
                172 RETURN_VALUE
            >>  174 SWAP                     2
                176 POP_TOP
    
     48         178 SWAP                     2
                180 STORE_FAST               1 (entry)
                182 RERAISE                  0
    ExceptionTable:
      118 to 162 -> 174 [6]

  ## code_object: build_trace_title
  filename: C:\Users\renan\OneDrive\Documents\New Era Glasses\src\new_era\application\use_cases\get_session_trace.py
  first_line: 52
  argcount: 1
  locals: 1
  stacksize: 4
  flags: 16777219
  names: ['event_type', 'EventType', 'OBSERVATION_CREATED', 'ALERT_CANDIDATE_CREATED', 'ALERT_SHOWN', 'ALERT_SUPPRESSED', 'LENS_COMMAND_DELIVERED', 'DEVICE_CAPABILITY_MISSING', 'DEVICE_DELIVERY_FAILED', 'JOB_STARTED', 'JOB_STATUS_UPDATED', 'JOB_COMPLETED', 'JOB_FAILED', 'AI_CALL_FAILED', 'ALERT_FEEDBACK_GIVEN', 'value', 'replace', 'title']
  varnames: ['event']
  cellvars: []
  freevars: []
  disassembly:
   52           0 RESUME                   0
  
   53           2 LOAD_FAST                0 (event)
                4 LOAD_ATTR                0 (event_type)
               24 LOAD_GLOBAL              2 (EventType)
               34 LOAD_ATTR                4 (OBSERVATION_CREATED)
               54 COMPARE_OP              40 (==)
               58 POP_JUMP_IF_FALSE        1 (to 62)
  
   54          60 RETURN_CONST             1 ('Observation captured')
  
   55     >>   62 LOAD_FAST                0 (event)
               64 LOAD_ATTR                0 (event_type)
               84 LOAD_GLOBAL              2 (EventType)
               94 LOAD_ATTR                6 (ALERT_CANDIDATE_CREATED)
              114 COMPARE_OP              40 (==)
              118 POP_JUMP_IF_FALSE        1 (to 122)
  
   56         120 RETURN_CONST             2 ('Alert candidate created')
  
   57     >>  122 LOAD_FAST                0 (event)
              124 LOAD_ATTR                0 (event_type)
              144 LOAD_GLOBAL              2 (EventType)
              154 LOAD_ATTR                8 (ALERT_SHOWN)
              174 COMPARE_OP              40 (==)
              178 POP_JUMP_IF_FALSE        1 (to 182)
  
   58         180 RETURN_CONST             3 ('Attention policy allowed display')
  
   59     >>  182 LOAD_FAST                0 (event)
              184 LOAD_ATTR                0 (event_type)
              204 LOAD_GLOBAL              2 (EventType)
              214 LOAD_ATTR               10 (ALERT_SUPPRESSED)
              234 COMPARE_OP              40 (==)
              238 POP_JUMP_IF_FALSE        1 (to 242)
  
   60         240 RETURN_CONST             4 ('Attention policy suppressed alert')
  
   61     >>  242 LOAD_FAST                0 (event)
              244 LOAD_ATTR                0 (event_type)
              264 LOAD_GLOBAL              2 (EventType)
              274 LOAD_ATTR               12 (LENS_COMMAND_DELIVERED)
              294 COMPARE_OP              40 (==)
              298 POP_JUMP_IF_FALSE        1 (to 302)
  
   62         300 RETURN_CONST             5 ('Lens command delivered')
  
   63     >>  302 LOAD_FAST                0 (event)
              304 LOAD_ATTR                0 (event_type)
              324 LOAD_GLOBAL              2 (EventType)
              334 LOAD_ATTR               14 (DEVICE_CAPABILITY_MISSING)
              354 COMPARE_OP              40 (==)
              358 POP_JUMP_IF_FALSE        1 (to 362)
  
   64         360 RETURN_CONST             6 ('Device capability missing')
  
   65     >>  362 LOAD_FAST                0 (event)
              364 LOAD_ATTR                0 (event_type)
              384 LOAD_GLOBAL              2 (EventType)
              394 LOAD_ATTR               16 (DEVICE_DELIVERY_FAILED)
              414 COMPARE_OP              40 (==)
              418 POP_JUMP_IF_FALSE        1 (to 422)
  
   66         420 RETURN_CONST             7 ('Device delivery failed')
  
   67     >>  422 LOAD_FAST                0 (event)
              424 LOAD_ATTR                0 (event_type)
              444 LOAD_GLOBAL              2 (EventType)
              454 LOAD_ATTR               18 (JOB_STARTED)
              474 COMPARE_OP              40 (==)
              478 POP_JUMP_IF_FALSE        1 (to 482)
  
   68         480 RETURN_CONST             8 ('Document analysis job accepted')
  
   69     >>  482 LOAD_FAST                0 (event)
              484 LOAD_ATTR                0 (event_type)
              504 LOAD_GLOBAL              2 (EventType)
              514 LOAD_ATTR               20 (JOB_STATUS_UPDATED)
              534 COMPARE_OP              40 (==)
              538 POP_JUMP_IF_FALSE        1 (to 542)
  
   70         540 RETURN_CONST             9 ('Document analysis job updated')
  
   71     >>  542 LOAD_FAST                0 (event)
              544 LOAD_ATTR                0 (event_type)
              564 LOAD_GLOBAL              2 (EventType)
              574 LOAD_ATTR               22 (JOB_COMPLETED)
              594 COMPARE_OP              40 (==)
              598 POP_JUMP_IF_FALSE        1 (to 602)
  
   72         600 RETURN_CONST            10 ('Document analysis job completed')
  
   73     >>  602 LOAD_FAST                0 (event)
              604 LOAD_ATTR                0 (event_type)
              624 LOAD_GLOBAL              2 (EventType)
              634 LOAD_ATTR               24 (JOB_FAILED)
              654 COMPARE_OP              40 (==)
              658 POP_JUMP_IF_FALSE        1 (to 662)
  
   74         660 RETURN_CONST            11 ('Document analysis job failed')
  
   75     >>  662 LOAD_FAST                0 (event)
              664 LOAD_ATTR                0 (event_type)
              684 LOAD_GLOBAL              2 (EventType)
              694 LOAD_ATTR               26 (AI_CALL_FAILED)
              714 COMPARE_OP              40 (==)
              718 POP_JUMP_IF_FALSE        1 (to 722)
  
   76         720 RETURN_CONST            12 ('Document analysis attempt failed')
  
   77     >>  722 LOAD_FAST                0 (event)
              724 LOAD_ATTR                0 (event_type)
              744 LOAD_GLOBAL              2 (EventType)
              754 LOAD_ATTR               28 (ALERT_FEEDBACK_GIVEN)
              774 COMPARE_OP              40 (==)
              778 POP_JUMP_IF_FALSE        1 (to 782)
  
   78         780 RETURN_CONST            13 ('Lens feedback recorded')
  
   79     >>  782 LOAD_FAST                0 (event)
              784 LOAD_ATTR                0 (event_type)
              804 LOAD_ATTR               30 (value)
              824 LOAD_ATTR               33 (NULL|self + replace)
              844 LOAD_CONST              14 ('_')
              846 LOAD_CONST              15 (' ')
              848 CALL                     2
              856 LOAD_ATTR               35 (NULL|self + title)
              876 CALL                     0
              884 RETURN_VALUE

  ## code_object: build_trace_detail
  filename: C:\Users\renan\OneDrive\Documents\New Era Glasses\src\new_era\application\use_cases\get_session_trace.py
  first_line: 82
  argcount: 1
  locals: 6
  stacksize: 7
  flags: 16777219
  names: ['metadata', 'event_type', 'EventType', 'OBSERVATION_CREATED', 'str', 'get', 'ALERT_CANDIDATE_CREATED', 'replace', 'ALERT_SHOWN', 'ALERT_SUPPRESSED', 'LENS_COMMAND_DELIVERED', 'DEVICE_CAPABILITY_MISSING', 'DEVICE_DELIVERY_FAILED', 'JOB_STARTED', 'JOB_STATUS_UPDATED', 'JOB_COMPLETED', 'JOB_FAILED', 'AI_CALL_FAILED', 'ALERT_FEEDBACK_GIVEN']
  varnames: ['event', 'metadata', 'priority', 'confidence', 'retry_text', 'feedback']
  cellvars: []
  freevars: []
  disassembly:
   82           0 RESUME                   0
  
   83           2 LOAD_FAST                0 (event)
                4 LOAD_ATTR                0 (metadata)
               24 STORE_FAST               1 (metadata)
  
   84          26 LOAD_FAST                0 (event)
               28 LOAD_ATTR                2 (event_type)
               48 LOAD_GLOBAL              4 (EventType)
               58 LOAD_ATTR                6 (OBSERVATION_CREATED)
               78 COMPARE_OP              40 (==)
               82 POP_JUMP_IF_FALSE       27 (to 138)
  
   85          84 LOAD_GLOBAL              9 (NULL + str)
               94 LOAD_FAST                1 (metadata)
               96 LOAD_ATTR               11 (NULL|self + get)
              116 LOAD_CONST               1 ('summary')
              118 LOAD_CONST               2 ('Observation received.')
              120 CALL                     2
              128 CALL                     1
              136 RETURN_VALUE
  
   86     >>  138 LOAD_FAST                0 (event)
              140 LOAD_ATTR                2 (event_type)
              160 LOAD_GLOBAL              4 (EventType)
              170 LOAD_ATTR               12 (ALERT_CANDIDATE_CREATED)
              190 COMPARE_OP              40 (==)
              194 POP_JUMP_IF_FALSE       87 (to 370)
  
   87         196 LOAD_GLOBAL              9 (NULL + str)
              206 LOAD_FAST                1 (metadata)
              208 LOAD_ATTR               11 (NULL|self + get)
              228 LOAD_CONST               3 ('priority')
              230 LOAD_CONST               4 ('unknown')
              232 CALL                     2
              240 CALL                     1
              248 LOAD_ATTR               15 (NULL|self + replace)
              268 LOAD_CONST               5 ('_')
              270 LOAD_CONST               6 (' ')
              272 CALL                     2
              280 STORE_FAST               2 (priority)
  
   88         282 LOAD_FAST                1 (metadata)
              284 LOAD_ATTR               11 (NULL|self + get)
              304 LOAD_CONST               7 ('confidence')
              306 CALL                     1
              314 STORE_FAST               3 (confidence)
  
   90         316 LOAD_FAST                1 (metadata)
              318 LOAD_ATTR               11 (NULL|self + get)
              338 LOAD_CONST               8 ('alert_type')
              340 LOAD_CONST               9 ('alert')
              342 CALL                     2
              350 FORMAT_VALUE             0
              352 LOAD_CONST              10 (' candidate with ')
  
   91         354 LOAD_FAST                2 (priority)
              356 FORMAT_VALUE             0
              358 LOAD_CONST              11 (' priority at confidence ')
              360 LOAD_FAST                3 (confidence)
              362 FORMAT_VALUE             0
              364 LOAD_CONST              12 ('.')
  
   90         366 BUILD_STRING             6
  
   89         368 RETURN_VALUE
  
   93     >>  370 LOAD_FAST                0 (event)
              372 LOAD_ATTR                2 (event_type)
              392 LOAD_GLOBAL              4 (EventType)
              402 LOAD_ATTR               16 (ALERT_SHOWN)
              422 LOAD_GLOBAL              4 (EventType)
              432 LOAD_ATTR               18 (ALERT_SUPPRESSED)
              452 BUILD_TUPLE              2
              454 CONTAINS_OP              0
              456 POP_JUMP_IF_FALSE       27 (to 512)
  
   94         458 LOAD_GLOBAL              9 (NULL + str)
              468 LOAD_FAST                1 (metadata)
              470 LOAD_ATTR               11 (NULL|self + get)
              490 LOAD_CONST              13 ('reason')
              492 LOAD_CONST              14 ('No decision reason recorded.')
              494 CALL                     2
              502 CALL                     1
              510 RETURN_VALUE
  
   95     >>  512 LOAD_FAST                0 (event)
              514 LOAD_ATTR                2 (event_type)
              534 LOAD_GLOBAL              4 (EventType)
              544 LOAD_ATTR               20 (LENS_COMMAND_DELIVERED)
              564 COMPARE_OP              40 (==)
              568 POP_JUMP_IF_FALSE       22 (to 614)
  
   96         570 LOAD_CONST              15 ('Rendered by ')
              572 LOAD_FAST                1 (metadata)
              574 LOAD_ATTR               11 (NULL|self + get)
              594 LOAD_CONST              16 ('adapter_name')
              596 LOAD_CONST              17 ('device adapter')
              598 CALL                     2
              606 FORMAT_VALUE             0
              608 LOAD_CONST              12 ('.')
              610 BUILD_STRING             3
              612 RETURN_VALUE
  
   97     >>  614 LOAD_FAST                0 (event)
              616 LOAD_ATTR                2 (event_type)
              636 LOAD_GLOBAL              4 (EventType)
              646 LOAD_ATTR               22 (DEVICE_CAPABILITY_MISSING)
              666 COMPARE_OP              40 (==)
              670 POP_JUMP_IF_FALSE       41 (to 754)
  
   99         672 LOAD_CONST              18 ('Missing ')
              674 LOAD_FAST                1 (metadata)
              676 LOAD_ATTR               11 (NULL|self + get)
              696 LOAD_CONST              19 ('missing_capability')
              698 LOAD_CONST              20 ('required capability')
              700 CALL                     2
              708 FORMAT_VALUE             0
              710 LOAD_CONST              21 (' on ')
  
  100         712 LOAD_FAST                1 (metadata)
              714 LOAD_ATTR               11 (NULL|self + get)
              734 LOAD_CONST              16 ('adapter_name')
              736 LOAD_CONST              17 ('device adapter')
              738 CALL                     2
              746 FORMAT_VALUE             0
              748 LOAD_CONST              12 ('.')
  
   99         750 BUILD_STRING             5
  
   98         752 RETURN_VALUE
  
  102     >>  754 LOAD_FAST                0 (event)
              756 LOAD_ATTR                2 (event_type)
              776 LOAD_GLOBAL              4 (EventType)
              786 LOAD_ATTR               24 (DEVICE_DELIVERY_FAILED)
              806 COMPARE_OP              40 (==)
              810 POP_JUMP_IF_FALSE       22 (to 856)
  
  103         812 LOAD_CONST              22 ('Delivery failed on ')
              814 LOAD_FAST                1 (metadata)
              816 LOAD_ATTR               11 (NULL|self + get)
              836 LOAD_CONST              16 ('adapter_name')
              838 LOAD_CONST              17 ('device adapter')
              840 CALL                     2
              848 FORMAT_VALUE             0
              850 LOAD_CONST              12 ('.')
              852 BUILD_STRING             3
              854 RETURN_VALUE
  
  104     >>  856 LOAD_FAST                0 (event)
              858 LOAD_ATTR                2 (event_type)
              878 LOAD_GLOBAL              4 (EventType)
              888 LOAD_ATTR               26 (JOB_STARTED)
              908 COMPARE_OP              40 (==)
              912 POP_JUMP_IF_FALSE       41 (to 996)
  
  106         914 LOAD_CONST              23 ('Queued ')
              916 LOAD_FAST                1 (metadata)
              918 LOAD_ATTR               11 (NULL|self + get)
              938 LOAD_CONST              24 ('job_type')
              940 LOAD_CONST              25 ('job')
              942 CALL                     2
              950 FORMAT_VALUE             0
              952 LOAD_CONST              26 (' for ')
  
  107         954 LOAD_FAST                1 (metadata)
              956 LOAD_ATTR               11 (NULL|self + get)
              976 LOAD_CONST              27 ('artifact_label')
              978 LOAD_CONST              28 ('document artifact')
              980 CALL                     2
              988 FORMAT_VALUE             0
              990 LOAD_CONST              12 ('.')
  
  106         992 BUILD_STRING             5
  
  105         994 RETURN_VALUE
  
  109     >>  996 LOAD_FAST                0 (event)
              998 LOAD_ATTR                2 (event_type)
             1018 LOAD_GLOBAL              4 (EventType)
             1028 LOAD_ATTR               28 (JOB_STATUS_UPDATED)
             1048 COMPARE_OP              40 (==)
             1052 POP_JUMP_IF_FALSE       41 (to 1136)
  
  111        1054 LOAD_CONST              29 ('Moved job from ')
             1056 LOAD_FAST                1 (metadata)
             1058 LOAD_ATTR               11 (NULL|self + get)
             1078 LOAD_CONST              30 ('from_status')
             1080 LOAD_CONST               4 ('unknown')
             1082 CALL                     2
             1090 FORMAT_VALUE             0
             1092 LOAD_CONST              31 (' to ')
  
  112        1094 LOAD_FAST                1 (metadata)
             1096 LOAD_ATTR               11 (NULL|self + get)
             1116 LOAD_CONST              32 ('to_status')
             1118 LOAD_CONST               4 ('unknown')
             1120 CALL                     2
             1128 FORMAT_VALUE             0
             1130 LOAD_CONST              12 ('.')
  
  111        1132 BUILD_STRING             5
  
  110        1134 RETURN_VALUE
  
  114     >> 1136 LOAD_FAST                0 (event)
             1138 LOAD_ATTR                2 (event_type)
             1158 LOAD_GLOBAL              4 (EventType)
             1168 LOAD_ATTR               30 (JOB_COMPLETED)
             1188 COMPARE_OP              40 (==)
             1192 POP_JUMP_IF_FALSE       22 (to 1238)
  
  115        1194 LOAD_CONST              33 ('Completed ')
             1196 LOAD_FAST                1 (metadata)
             1198 LOAD_ATTR               11 (NULL|self + get)
             1218 LOAD_CONST              24 ('job_type')
             1220 LOAD_CONST              25 ('job')
             1222 CALL                     2
             1230 FORMAT_VALUE             0
             1232 LOAD_CONST              12 ('.')
             1234 BUILD_STRING             3
             1236 RETURN_VALUE
  
  116     >> 1238 LOAD_FAST                0 (event)
             1240 LOAD_ATTR                2 (event_type)
             1260 LOAD_GLOBAL              4 (EventType)
             1270 LOAD_ATTR               32 (JOB_FAILED)
             1290 COMPARE_OP              40 (==)
             1294 POP_JUMP_IF_FALSE       22 (to 1340)
  
  117        1296 LOAD_CONST              34 ('Failed ')
             1298 LOAD_FAST                1 (metadata)
             1300 LOAD_ATTR               11 (NULL|self + get)
             1320 LOAD_CONST              24 ('job_type')
             1322 LOAD_CONST              25 ('job')
             1324 CALL                     2
             1332 FORMAT_VALUE             0
             1334 LOAD_CONST              12 ('.')
             1336 BUILD_STRING             3
             1338 RETURN_VALUE
  
  118     >> 1340 LOAD_FAST                0 (event)
             1342 LOAD_ATTR                2 (event_type)
             1362 LOAD_GLOBAL              4 (EventType)
             1372 LOAD_ATTR               34 (AI_CALL_FAILED)
             1392 COMPARE_OP              40 (==)
             1396 POP_JUMP_IF_FALSE       46 (to 1490)
  
  119        1398 LOAD_FAST                1 (metadata)
             1400 LOAD_ATTR               11 (NULL|self + get)
             1420 LOAD_CONST              35 ('retry_scheduled')
             1422 CALL                     1
             1430 POP_JUMP_IF_FALSE        2 (to 1436)
             1432 LOAD_CONST              36 ('retry scheduled')
             1434 JUMP_FORWARD             1 (to 1438)
          >> 1436 LOAD_CONST              37 ('no retry')
          >> 1438 STORE_FAST               4 (retry_text)
  
  120        1440 LOAD_CONST              38 ('Attempt ')
             1442 LOAD_FAST                1 (metadata)
             1444 LOAD_ATTR               11 (NULL|self + get)
             1464 LOAD_CONST              39 ('attempt')
             1466 LOAD_CONST               4 ('unknown')
             1468 CALL                     2
             1476 FORMAT_VALUE             0
             1478 LOAD_CONST              40 (' failed; ')
             1480 LOAD_FAST                4 (retry_text)
             1482 FORMAT_VALUE             0
             1484 LOAD_CONST              12 ('.')
             1486 BUILD_STRING             5
             1488 RETURN_VALUE
  
  121     >> 1490 LOAD_FAST                0 (event)
             1492 LOAD_ATTR                2 (event_type)
             1512 LOAD_GLOBAL              4 (EventType)
             1522 LOAD_ATTR               36 (ALERT_FEEDBACK_GIVEN)
             1542 COMPARE_OP              40 (==)
             1546 POP_JUMP_IF_FALSE       49 (to 1646)
  
  122        1548 LOAD_GLOBAL              9 (NULL + str)
             1558 LOAD_FAST                1 (metadata)
             1560 LOAD_ATTR               11 (NULL|self + get)
             1580 LOAD_CONST              41 ('feedback')
             1582 LOAD_CONST              41 ('feedback')
             1584 CALL                     2
             1592 CALL                     1
             1600 LOAD_ATTR               15 (NULL|self + replace)
             1620 LOAD_CONST               5 ('_')
             1622 LOAD_CONST               6 (' ')
             1624 CALL                     2
             1632 STORE_FAST               5 (feedback)
  
  123        1634 LOAD_CONST              42 ('Marked the lens alert as ')
             1636 LOAD_FAST                5 (feedback)
             1638 FORMAT_VALUE             0
             1640 LOAD_CONST              12 ('.')
             1642 BUILD_STRING             3
             1644 RETURN_VALUE
  
  124     >> 1646 RETURN_CONST            43 ('Event recorded.')

  ## code_object: build_trace_step
  filename: C:\Users\renan\OneDrive\Documents\New Era Glasses\src\new_era\application\use_cases\get_session_trace.py
  first_line: 127
  argcount: 1
  locals: 1
  stacksize: 5
  flags: 16777219
  names: ['EventType', 'OBSERVATION_CREATED', 'ALERT_CANDIDATE_CREATED', 'ALERT_SHOWN', 'ALERT_SUPPRESSED', 'LENS_COMMAND_DELIVERED', 'DEVICE_CAPABILITY_MISSING', 'DEVICE_DELIVERY_FAILED', 'JOB_STARTED', 'JOB_STATUS_UPDATED', 'JOB_COMPLETED', 'JOB_FAILED', 'AI_CALL_FAILED', 'ALERT_FEEDBACK_GIVEN']
  varnames: ['event_type']
  cellvars: []
  freevars: []
  disassembly:
  127           0 RESUME                   0
  
  128           2 LOAD_FAST                0 (event_type)
                4 LOAD_GLOBAL              0 (EventType)
               14 LOAD_ATTR                2 (OBSERVATION_CREATED)
               34 COMPARE_OP              40 (==)
               38 POP_JUMP_IF_FALSE        1 (to 42)
  
  129          40 RETURN_CONST             1 ('observation')
  
  130     >>   42 LOAD_FAST                0 (event_type)
               44 LOAD_GLOBAL              0 (EventType)
               54 LOAD_ATTR                4 (ALERT_CANDIDATE_CREATED)
               74 COMPARE_OP              40 (==)
               78 POP_JUMP_IF_FALSE        1 (to 82)
  
  131          80 RETURN_CONST             2 ('candidate')
  
  132     >>   82 LOAD_FAST                0 (event_type)
               84 LOAD_GLOBAL              0 (EventType)
               94 LOAD_ATTR                6 (ALERT_SHOWN)
              114 LOAD_GLOBAL              0 (EventType)
              124 LOAD_ATTR                8 (ALERT_SUPPRESSED)
              144 BUILD_TUPLE              2
              146 CONTAINS_OP              0
              148 POP_JUMP_IF_FALSE        1 (to 152)
  
  133         150 RETURN_CONST             3 ('decision')
  
  134     >>  152 LOAD_FAST                0 (event_type)
  
  135         154 LOAD_GLOBAL              0 (EventType)
              164 LOAD_ATTR               10 (LENS_COMMAND_DELIVERED)
  
  136         184 LOAD_GLOBAL              0 (EventType)
              194 LOAD_ATTR               12 (DEVICE_CAPABILITY_MISSING)
  
  137         214 LOAD_GLOBAL              0 (EventType)
              224 LOAD_ATTR               14 (DEVICE_DELIVERY_FAILED)
  
  134         244 BUILD_TUPLE              3
              246 CONTAINS_OP              0
              248 POP_JUMP_IF_FALSE        1 (to 252)
  
  139         250 RETURN_CONST             4 ('delivery')
  
  140     >>  252 LOAD_FAST                0 (event_type)
  
  141         254 LOAD_GLOBAL              0 (EventType)
              264 LOAD_ATTR               16 (JOB_STARTED)
  
  142         284 LOAD_GLOBAL              0 (EventType)
              294 LOAD_ATTR               18 (JOB_STATUS_UPDATED)
  
  143         314 LOAD_GLOBAL              0 (EventType)
              324 LOAD_ATTR               20 (JOB_COMPLETED)
  
  144         344 LOAD_GLOBAL              0 (EventType)
              354 LOAD_ATTR               22 (JOB_FAILED)
  
  140         374 BUILD_TUPLE              4
              376 CONTAINS_OP              0
              378 POP_JUMP_IF_FALSE        1 (to 382)
  
  146         380 RETURN_CONST             5 ('job')
  
  147     >>  382 LOAD_FAST                0 (event_type)
              384 LOAD_GLOBAL              0 (EventType)
              394 LOAD_ATTR               24 (AI_CALL_FAILED)
              414 COMPARE_OP              40 (==)
              418 POP_JUMP_IF_FALSE        1 (to 422)
  
  148         420 RETURN_CONST             6 ('provider')
  
  149     >>  422 LOAD_FAST                0 (event_type)
              424 LOAD_GLOBAL              0 (EventType)
              434 LOAD_ATTR               26 (ALERT_FEEDBACK_GIVEN)
              454 COMPARE_OP              40 (==)
              458 POP_JUMP_IF_FALSE        1 (to 462)
  
  150         460 RETURN_CONST             7 ('feedback')
  
  151     >>  462 RETURN_CONST             8 ('system')

  ## code_object: normalize_trace_limit
  filename: C:\Users\renan\OneDrive\Documents\New Era Glasses\src\new_era\application\use_cases\get_session_trace.py
  first_line: 174
  argcount: 1
  locals: 1
  stacksize: 4
  flags: 16777219
  names: ['DEFAULT_TRACE_LIMIT', 'ValueError', 'min', 'MAX_TRACE_LIMIT']
  varnames: ['limit']
  cellvars: []
  freevars: []
  disassembly:
  174           0 RESUME                   0
  
  175           2 LOAD_FAST                0 (limit)
                4 POP_JUMP_IF_NOT_NONE     6 (to 18)
  
  176           6 LOAD_GLOBAL              0 (DEFAULT_TRACE_LIMIT)
               16 RETURN_VALUE
  
  177     >>   18 LOAD_FAST                0 (limit)
               20 LOAD_CONST               1 (1)
               22 COMPARE_OP               2 (<)
               26 POP_JUMP_IF_FALSE       11 (to 50)
  
  178          28 LOAD_GLOBAL              3 (NULL + ValueError)
               38 LOAD_CONST               2 ('limit must be at least 1')
               40 CALL                     1
               48 RAISE_VARARGS            1
  
  179     >>   50 LOAD_GLOBAL              5 (NULL + min)
               60 LOAD_FAST                0 (limit)
               62 LOAD_GLOBAL              6 (MAX_TRACE_LIMIT)
               72 CALL                     2
               80 RETURN_VALUE

  ## code_object: encode_trace_cursor
  filename: C:\Users\renan\OneDrive\Documents\New Era Glasses\src\new_era\application\use_cases\get_session_trace.py
  first_line: 182
  argcount: 1
  locals: 2
  stacksize: 5
  flags: 16777219
  names: ['created_at', 'isoformat', 'event_id', 'urlsafe_b64encode', 'encode', 'decode']
  varnames: ['event', 'value']
  cellvars: []
  freevars: []
  disassembly:
  182           0 RESUME                   0
  
  183           2 LOAD_FAST                0 (event)
                4 LOAD_ATTR                0 (created_at)
               24 LOAD_ATTR                3 (NULL|self + isoformat)
               44 CALL                     0
               52 FORMAT_VALUE             0
               54 LOAD_CONST               1 ('|')
               56 LOAD_FAST                0 (event)
               58 LOAD_ATTR                4 (event_id)
               78 FORMAT_VALUE             0
               80 BUILD_STRING             3
               82 STORE_FAST               1 (value)
  
  184          84 LOAD_GLOBAL              7 (NULL + urlsafe_b64encode)
               94 LOAD_FAST                1 (value)
               96 LOAD_ATTR                9 (NULL|self + encode)
              116 LOAD_CONST               2 ('utf-8')
              118 CALL                     1
              126 CALL                     1
              134 LOAD_ATTR               11 (NULL|self + decode)
              154 LOAD_CONST               3 ('ascii')
              156 CALL                     1
              164 RETURN_VALUE

  ## code_object: decode_trace_cursor
  filename: C:\Users\renan\OneDrive\Documents\New Era Glasses\src\new_era\application\use_cases\get_session_trace.py
  first_line: 187
  argcount: 1
  locals: 5
  stacksize: 5
  flags: 16777219
  names: ['urlsafe_b64decode', 'encode', 'decode', 'split', 'datetime', 'fromisoformat', 'Exception', 'ValueError']
  varnames: ['cursor', 'decoded', 'created_at_text', 'event_id', 'exc']
  cellvars: []
  freevars: []
  disassembly:
  187           0 RESUME                   0
  
  188           2 LOAD_FAST                0 (cursor)
                4 POP_JUMP_IF_NOT_NONE     1 (to 8)
  
  189           6 RETURN_CONST             0 (None)
  
  190     >>    8 NOP
  
  191          10 LOAD_GLOBAL              1 (NULL + urlsafe_b64decode)
               20 LOAD_FAST                0 (cursor)
               22 LOAD_ATTR                3 (NULL|self + encode)
               42 LOAD_CONST               1 ('ascii')
               44 CALL                     1
               52 CALL                     1
               60 LOAD_ATTR                5 (NULL|self + decode)
               80 LOAD_CONST               2 ('utf-8')
               82 CALL                     1
               90 STORE_FAST               1 (decoded)
  
  192          92 LOAD_FAST                1 (decoded)
               94 LOAD_ATTR                7 (NULL|self + split)
              114 LOAD_CONST               3 ('|')
              116 LOAD_CONST               4 (1)
              118 CALL                     2
              126 UNPACK_SEQUENCE          2
              130 STORE_FAST               2 (created_at_text)
              132 STORE_FAST               3 (event_id)
  
  193         134 LOAD_GLOBAL              9 (NULL + datetime)
              144 LOAD_ATTR               10 (fromisoformat)
              164 LOAD_FAST                2 (created_at_text)
              166 CALL                     1
              174 LOAD_FAST                3 (event_id)
              176 BUILD_TUPLE              2
              178 RETURN_VALUE
          >>  180 PUSH_EXC_INFO
  
  194         182 LOAD_GLOBAL             12 (Exception)
              192 CHECK_EXC_MATCH
              194 POP_JUMP_IF_FALSE       17 (to 230)
              196 STORE_FAST               4 (exc)
  
  195         198 LOAD_GLOBAL             15 (NULL + ValueError)
              208 LOAD_CONST               5 ('invalid trace cursor')
              210 CALL                     1
              218 LOAD_FAST                4 (exc)
              220 RAISE_VARARGS            2
          >>  222 LOAD_CONST               0 (None)
              224 STORE_FAST               4 (exc)
              226 DELETE_FAST              4 (exc)
              228 RERAISE                  1
  
  194     >>  230 RERAISE                  0
          >>  232 COPY                     3
              234 POP_EXCEPT
              236 RERAISE                  1
  ExceptionTable:
    10 to 176 -> 180 [0]
    180 to 196 -> 232 [1] lasti
    198 to 220 -> 222 [1] lasti
    222 to 230 -> 232 [1] lasti

  ## code_object: event_types_for_steps
  filename: C:\Users\renan\OneDrive\Documents\New Era Glasses\src\new_era\application\use_cases\get_session_trace.py
  first_line: 198
  argcount: 1
  locals: 5
  stacksize: 5
  flags: 16777219
  names: ['difference', 'TRACE_STEP_EVENT_TYPES', 'keys', 'join', 'sorted', 'ValueError', 'set', 'update']
  varnames: ['steps', 'unknown_steps', 'names', 'event_types', 'step']
  cellvars: []
  freevars: []
  disassembly:
  198           0 RESUME                   0
  
  199           2 LOAD_FAST                0 (steps)
                4 POP_JUMP_IF_TRUE         1 (to 8)
  
  200           6 RETURN_CONST             0 (None)
  
  201     >>    8 LOAD_FAST                0 (steps)
               10 LOAD_ATTR                1 (NULL|self + difference)
               30 LOAD_GLOBAL              2 (TRACE_STEP_EVENT_TYPES)
               40 LOAD_ATTR                5 (NULL|self + keys)
               60 CALL                     0
               68 CALL                     1
               76 STORE_FAST               1 (unknown_steps)
  
  202          78 LOAD_FAST                1 (unknown_steps)
               80 POP_JUMP_IF_FALSE       40 (to 162)
  
  203          82 LOAD_CONST               1 (', ')
               84 LOAD_ATTR                7 (NULL|self + join)
              104 LOAD_GLOBAL              9 (NULL + sorted)
              114 LOAD_FAST                1 (unknown_steps)
              116 CALL                     1
              124 CALL                     1
              132 STORE_FAST               2 (names)
  
  204         134 LOAD_GLOBAL             11 (NULL + ValueError)
              144 LOAD_CONST               2 ('unknown trace step filter: ')
              146 LOAD_FAST                2 (names)
              148 FORMAT_VALUE             0
              150 BUILD_STRING             2
              152 CALL                     1
              160 RAISE_VARARGS            1
  
  206     >>  162 LOAD_GLOBAL             13 (NULL + set)
              172 CALL                     0
              180 STORE_FAST               3 (event_types)
  
  207         182 LOAD_FAST                0 (steps)
              184 GET_ITER
          >>  186 FOR_ITER                26 (to 242)
              190 STORE_FAST               4 (step)
  
  208         192 LOAD_FAST                3 (event_types)
              194 LOAD_ATTR               15 (NULL|self + update)
              214 LOAD_GLOBAL              2 (TRACE_STEP_EVENT_TYPES)
              224 LOAD_FAST                4 (step)
              226 BINARY_SUBSCR
              230 CALL                     1
              238 POP_TOP
              240 JUMP_BACKWARD           28 (to 186)
  
  207     >>  242 END_FOR
  
  209         244 LOAD_FAST                3 (event_types)
              246 RETURN_VALUE

  ## code_object: combine_event_type_filters
  filename: C:\Users\renan\OneDrive\Documents\New Era Glasses\src\new_era\application\use_cases\get_session_trace.py
  first_line: 212
  argcount: 0
  locals: 3
  stacksize: 3
  flags: 16777219
  names: ['event_types_for_steps', 'intersection']
  varnames: ['event_types', 'steps', 'step_event_types']
  cellvars: []
  freevars: []
  disassembly:
  212           0 RESUME                   0
  
  217           2 LOAD_GLOBAL              1 (NULL + event_types_for_steps)
               12 LOAD_FAST                1 (steps)
               14 CALL                     1
               22 STORE_FAST               2 (step_event_types)
  
  218          24 LOAD_FAST                0 (event_types)
               26 POP_JUMP_IF_NOT_NONE     2 (to 32)
  
  219          28 LOAD_FAST                2 (step_event_types)
               30 RETURN_VALUE
  
  220     >>   32 LOAD_FAST                2 (step_event_types)
               34 POP_JUMP_IF_NOT_NONE     2 (to 40)
  
  221          36 LOAD_FAST                0 (event_types)
               38 RETURN_VALUE
  
  222     >>   40 LOAD_FAST                0 (event_types)
               42 LOAD_ATTR                3 (NULL|self + intersection)
               62 LOAD_FAST                2 (step_event_types)
               64 CALL                     1
               72 RETURN_VALUE

  ## code_object: GetSessionTrace
  filename: C:\Users\renan\OneDrive\Documents\New Era Glasses\src\new_era\application\use_cases\get_session_trace.py
  first_line: 225
  argcount: 0
  locals: 0
  stacksize: 10
  flags: 16777216
  names: ['__name__', '__module__', '__qualname__', '__annotations__', 'execute']
  varnames: []
  cellvars: []
  freevars: []
  disassembly:
  225           0 RESUME                   0
                2 LOAD_NAME                0 (__name__)
                4 STORE_NAME               1 (__module__)
                6 LOAD_CONST               0 ('GetSessionTrace')
                8 STORE_NAME               2 (__qualname__)
               10 SETUP_ANNOTATIONS
  
  227          12 LOAD_CONST               1 ('EventStore')
               14 LOAD_NAME                3 (__annotations__)
               16 LOAD_CONST               2 ('event_store')
               18 STORE_SUBSCR
  
  233          22 LOAD_CONST               3 (None)
  
  234          24 LOAD_CONST               3 (None)
  
  235          26 LOAD_CONST               3 (None)
  
  236          28 LOAD_CONST               3 (None)
  
  237          30 LOAD_CONST               3 (None)
  
  238          32 LOAD_CONST               3 (None)
  
  239          34 LOAD_CONST               3 (None)
  
  240          36 LOAD_CONST               3 (None)
  
  241          38 LOAD_CONST               3 (None)
  
  229          40 LOAD_CONST               4 (('user_id', 'trace_id', 'module', 'event_types', 'steps', 'created_after', 'created_before', 'limit', 'cursor'))
               42 BUILD_CONST_KEY_MAP      9
  
  232          44 NOP
  
  229          46 NOP
  
  233          48 NOP
  
  229          50 NOP
  
  234          52 NOP
  
  229          54 NOP
  
  235          56 NOP
  
  229          58 NOP
  
  236          60 NOP
  
  229          62 NOP
  
  237          64 NOP
  
  229          66 NOP
  
  238          68 NOP
  
  229          70 NOP
  
  239          72 NOP
  
  229          74 NOP
  
  240          76 NOP
  
  229          78 NOP
  
  241          80 NOP
  
  229          82 NOP
  
  242          84 NOP
  
  229          86 LOAD_CONST               6 (('session_id', 'str', 'user_id', 'str | None', 'trace_id', 'str | None', 'module', 'str | None', 'event_types', 'set[EventType] | None', 'steps', 'set[str] | None', 'created_after', 'datetime | None', 'created_before', 'datetime | None', 'limit', 'int | None', 'cursor', 'str | None', 'return', 'SessionTraceReadModel'))
               88 LOAD_CONST               5 (<code object execute at 0x0000014940FFDE30, file "C:\Users\renan\OneDrive\Documents\New Era Glasses\src\new_era\application\use_cases\get_session_trace.py", line 229>)
               90 MAKE_FUNCTION            6 (kwdefaults, annotations)
               92 STORE_NAME               4 (execute)
               94 RETURN_CONST             3 (None)
  
  Disassembly of <code object execute at 0x0000014940FFDE30, file "C:\Users\renan\OneDrive\Documents\New Era Glasses\src\new_era\application\use_cases\get_session_trace.py", line 229>:
  229           0 RESUME                   0
  
  243           2 LOAD_GLOBAL              1 (NULL + normalize_trace_limit)
               12 LOAD_FAST                9 (limit)
               14 CALL                     1
               22 STORE_FAST              11 (normalized_limit)
  
  244          24 LOAD_GLOBAL              3 (NULL + combine_event_type_filters)
  
  245          34 LOAD_FAST                5 (event_types)
  
  246          36 LOAD_FAST                6 (steps)
  
  244          38 KW_NAMES                 1 (('event_types', 'steps'))
               40 CALL                     2
               48 STORE_FAST              12 (combined_event_types)
  
  248          50 LOAD_FAST                0 (self)
               52 LOAD_ATTR                4 (event_store)
               72 LOAD_ATTR                7 (NULL|self + list_events)
  
  249          92 LOAD_FAST                2 (user_id)
  
  250          94 LOAD_FAST                1 (session_id)
  
  251          96 LOAD_FAST                3 (trace_id)
  
  252          98 LOAD_FAST                4 (module)
  
  253         100 LOAD_FAST               12 (combined_event_types)
  
  254         102 LOAD_FAST                7 (created_after)
  
  255         104 LOAD_FAST                8 (created_before)
  
  256         106 LOAD_GLOBAL              9 (NULL + decode_trace_cursor)
              116 LOAD_FAST               10 (cursor)
              118 CALL                     1
  
  257         126 LOAD_FAST               11 (normalized_limit)
              128 LOAD_CONST               2 (1)
              130 BINARY_OP                0 (+)
  
  248         134 KW_NAMES                 3 (('user_id', 'session_id', 'trace_id', 'module', 'event_types', 'created_after', 'created_before', 'after', 'limit'))
              136 CALL                     9
              144 STORE_FAST              13 (events)
  
  259         146 LOAD_GLOBAL             11 (NULL + len)
              156 LOAD_FAST               13 (events)
              158 CALL                     1
              166 LOAD_FAST               11 (normalized_limit)
              168 COMPARE_OP              68 (>)
              172 STORE_FAST              14 (has_more)
  
  260         174 LOAD_FAST               13 (events)
              176 LOAD_CONST               0 (None)
              178 LOAD_FAST               11 (normalized_limit)
              180 BINARY_SLICE
              182 STORE_FAST              15 (page_events)
  
  261         184 LOAD_GLOBAL             13 (NULL + tuple)
              194 LOAD_CONST               4 (<code object <genexpr> at 0x0000014941124570, file "C:\Users\renan\OneDrive\Documents\New Era Glasses\src\new_era\application\use_cases\get_session_trace.py", line 261>)
              196 MAKE_FUNCTION            0
  
  270         198 LOAD_FAST               15 (page_events)
              200 GET_ITER
  
  261         202 CALL                     0
              210 CALL                     1
              218 STORE_FAST              16 (entries)
  
  272         220 LOAD_GLOBAL             15 (NULL + SessionTraceReadModel)
  
  273         230 LOAD_FAST                1 (session_id)
  
  274         232 LOAD_FAST                3 (trace_id)
  
  275         234 LOAD_GLOBAL             11 (NULL + len)
              244 LOAD_FAST               16 (entries)
              246 CALL                     1
  
  277         254 LOAD_FAST               14 (has_more)
              256 POP_JUMP_IF_FALSE       22 (to 302)
              258 LOAD_FAST               15 (page_events)
              260 POP_JUMP_IF_FALSE       20 (to 302)
  
  276         262 LOAD_GLOBAL             17 (NULL + encode_trace_cursor)
              272 LOAD_FAST               15 (page_events)
              274 LOAD_CONST               5 (-1)
              276 BINARY_SUBSCR
              280 CALL                     1
  
  279         288 LOAD_FAST               16 (entries)
  
  272         290 KW_NAMES                 6 (('session_id', 'trace_id', 'event_count', 'next_cursor', 'session_trace'))
              292 CALL                     5
              300 RETURN_VALUE
  
  278     >>  302 LOAD_CONST               0 (None)
  
  279         304 LOAD_FAST               16 (entries)
  
  272         306 KW_NAMES                 6 (('session_id', 'trace_id', 'event_count', 'next_cursor', 'session_trace'))
              308 CALL                     5
              316 RETURN_VALUE
  
  Disassembly of <code object <genexpr> at 0x0000014941124570, file "C:\Users\renan\OneDrive\Documents\New Era Glasses\src\new_era\application\use_cases\get_session_trace.py", line 261>:
  261           0 RETURN_GENERATOR
                2 POP_TOP
                4 RESUME                   0
                6 LOAD_FAST                0 (.0)
  
  270     >>    8 FOR_ITER               112 (to 236)
               12 STORE_FAST               1 (event)
  
  262          14 LOAD_GLOBAL              1 (NULL + SessionTraceEntry)
  
  263          24 LOAD_FAST                1 (event)
               26 LOAD_ATTR                2 (event_id)
  
  264          46 LOAD_FAST                1 (event)
               48 LOAD_ATTR                4 (event_type)
               68 LOAD_ATTR                6 (value)
  
  265          88 LOAD_GLOBAL              9 (NULL + build_trace_step)
               98 LOAD_FAST                1 (event)
              100 LOAD_ATTR                4 (event_type)
              120 CALL                     1
  
  266         128 LOAD_GLOBAL             11 (NULL + build_trace_title)
              138 LOAD_FAST                1 (event)
              140 CALL                     1
  
  267         148 LOAD_GLOBAL             13 (NULL + build_trace_detail)
              158 LOAD_FAST                1 (event)
              160 CALL                     1
  
  268         168 LOAD_FAST                1 (event)
              170 LOAD_ATTR               14 (created_at)
              190 LOAD_ATTR               17 (NULL|self + isoformat)
              210 CALL                     0
  
  262         218 KW_NAMES                 0 (('event_id', 'event_type', 'step', 'title', 'detail', 'created_at'))
              220 CALL                     6
              228 YIELD_VALUE              1
              230 RESUME                   1
              232 POP_TOP
              234 JUMP_BACKWARD          114 (to 8)
  
  270     >>  236 END_FOR
              238 RETURN_CONST             1 (None)
          >>  240 CALL_INTRINSIC_1         3 (INTRINSIC_STOPITERATION_ERROR)
              242 RERAISE                  1
  ExceptionTable:
    4 to 238 -> 240 [0] lasti

    ## code_object: execute
    filename: C:\Users\renan\OneDrive\Documents\New Era Glasses\src\new_era\application\use_cases\get_session_trace.py
    first_line: 229
    argcount: 1
    locals: 17
    stacksize: 12
    flags: 16777219
    names: ['normalize_trace_limit', 'combine_event_type_filters', 'event_store', 'list_events', 'decode_trace_cursor', 'len', 'tuple', 'SessionTraceReadModel', 'encode_trace_cursor']
    varnames: ['self', 'session_id', 'user_id', 'trace_id', 'module', 'event_types', 'steps', 'created_after', 'created_before', 'limit', 'cursor', 'normalized_limit', 'combined_event_types', 'events', 'has_more', 'page_events', 'entries']
    cellvars: []
    freevars: []
    disassembly:
    229           0 RESUME                   0
    
    243           2 LOAD_GLOBAL              1 (NULL + normalize_trace_limit)
                 12 LOAD_FAST                9 (limit)
                 14 CALL                     1
                 22 STORE_FAST              11 (normalized_limit)
    
    244          24 LOAD_GLOBAL              3 (NULL + combine_event_type_filters)
    
    245          34 LOAD_FAST                5 (event_types)
    
    246          36 LOAD_FAST                6 (steps)
    
    244          38 KW_NAMES                 1 (('event_types', 'steps'))
                 40 CALL                     2
                 48 STORE_FAST              12 (combined_event_types)
    
    248          50 LOAD_FAST                0 (self)
                 52 LOAD_ATTR                4 (event_store)
                 72 LOAD_ATTR                7 (NULL|self + list_events)
    
    249          92 LOAD_FAST                2 (user_id)
    
    250          94 LOAD_FAST                1 (session_id)
    
    251          96 LOAD_FAST                3 (trace_id)
    
    252          98 LOAD_FAST                4 (module)
    
    253         100 LOAD_FAST               12 (combined_event_types)
    
    254         102 LOAD_FAST                7 (created_after)
    
    255         104 LOAD_FAST                8 (created_before)
    
    256         106 LOAD_GLOBAL              9 (NULL + decode_trace_cursor)
                116 LOAD_FAST               10 (cursor)
                118 CALL                     1
    
    257         126 LOAD_FAST               11 (normalized_limit)
                128 LOAD_CONST               2 (1)
                130 BINARY_OP                0 (+)
    
    248         134 KW_NAMES                 3 (('user_id', 'session_id', 'trace_id', 'module', 'event_types', 'created_after', 'created_before', 'after', 'limit'))
                136 CALL                     9
                144 STORE_FAST              13 (events)
    
    259         146 LOAD_GLOBAL             11 (NULL + len)
                156 LOAD_FAST               13 (events)
                158 CALL                     1
                166 LOAD_FAST               11 (normalized_limit)
                168 COMPARE_OP              68 (>)
                172 STORE_FAST              14 (has_more)
    
    260         174 LOAD_FAST               13 (events)
                176 LOAD_CONST               0 (None)
                178 LOAD_FAST               11 (normalized_limit)
                180 BINARY_SLICE
                182 STORE_FAST              15 (page_events)
    
    261         184 LOAD_GLOBAL             13 (NULL + tuple)
                194 LOAD_CONST               4 (<code object <genexpr> at 0x0000014941124570, file "C:\Users\renan\OneDrive\Documents\New Era Glasses\src\new_era\application\use_cases\get_session_trace.py", line 261>)
                196 MAKE_FUNCTION            0
    
    270         198 LOAD_FAST               15 (page_events)
                200 GET_ITER
    
    261         202 CALL                     0
                210 CALL                     1
                218 STORE_FAST              16 (entries)
    
    272         220 LOAD_GLOBAL             15 (NULL + SessionTraceReadModel)
    
    273         230 LOAD_FAST                1 (session_id)
    
    274         232 LOAD_FAST                3 (trace_id)
    
    275         234 LOAD_GLOBAL             11 (NULL + len)
                244 LOAD_FAST               16 (entries)
                246 CALL                     1
    
    277         254 LOAD_FAST               14 (has_more)
                256 POP_JUMP_IF_FALSE       22 (to 302)
                258 LOAD_FAST               15 (page_events)
                260 POP_JUMP_IF_FALSE       20 (to 302)
    
    276         262 LOAD_GLOBAL             17 (NULL + encode_trace_cursor)
                272 LOAD_FAST               15 (page_events)
                274 LOAD_CONST               5 (-1)
                276 BINARY_SUBSCR
                280 CALL                     1
    
    279         288 LOAD_FAST               16 (entries)
    
    272         290 KW_NAMES                 6 (('session_id', 'trace_id', 'event_count', 'next_cursor', 'session_trace'))
                292 CALL                     5
                300 RETURN_VALUE
    
    278     >>  302 LOAD_CONST               0 (None)
    
    279         304 LOAD_FAST               16 (entries)
    
    272         306 KW_NAMES                 6 (('session_id', 'trace_id', 'event_count', 'next_cursor', 'session_trace'))
                308 CALL                     5
                316 RETURN_VALUE
    
    Disassembly of <code object <genexpr> at 0x0000014941124570, file "C:\Users\renan\OneDrive\Documents\New Era Glasses\src\new_era\application\use_cases\get_session_trace.py", line 261>:
    261           0 RETURN_GENERATOR
                  2 POP_TOP
                  4 RESUME                   0
                  6 LOAD_FAST                0 (.0)
    
    270     >>    8 FOR_ITER               112 (to 236)
                 12 STORE_FAST               1 (event)
    
    262          14 LOAD_GLOBAL              1 (NULL + SessionTraceEntry)
    
    263          24 LOAD_FAST                1 (event)
                 26 LOAD_ATTR                2 (event_id)
    
    264          46 LOAD_FAST                1 (event)
                 48 LOAD_ATTR                4 (event_type)
                 68 LOAD_ATTR                6 (value)
    
    265          88 LOAD_GLOBAL              9 (NULL + build_trace_step)
                 98 LOAD_FAST                1 (event)
                100 LOAD_ATTR                4 (event_type)
                120 CALL                     1
    
    266         128 LOAD_GLOBAL             11 (NULL + build_trace_title)
                138 LOAD_FAST                1 (event)
                140 CALL                     1
    
    267         148 LOAD_GLOBAL             13 (NULL + build_trace_detail)
                158 LOAD_FAST                1 (event)
                160 CALL                     1
    
    268         168 LOAD_FAST                1 (event)
                170 LOAD_ATTR               14 (created_at)
                190 LOAD_ATTR               17 (NULL|self + isoformat)
                210 CALL                     0
    
    262         218 KW_NAMES                 0 (('event_id', 'event_type', 'step', 'title', 'detail', 'created_at'))
                220 CALL                     6
                228 YIELD_VALUE              1
                230 RESUME                   1
                232 POP_TOP
                234 JUMP_BACKWARD          114 (to 8)
    
    270     >>  236 END_FOR
                238 RETURN_CONST             1 (None)
            >>  240 CALL_INTRINSIC_1         3 (INTRINSIC_STOPITERATION_ERROR)
                242 RERAISE                  1
    ExceptionTable:
      4 to 238 -> 240 [0] lasti

      ## code_object: <genexpr>
      filename: C:\Users\renan\OneDrive\Documents\New Era Glasses\src\new_era\application\use_cases\get_session_trace.py
      first_line: 261
      argcount: 1
      locals: 2
      stacksize: 10
      flags: 16777267
      names: ['SessionTraceEntry', 'event_id', 'event_type', 'value', 'build_trace_step', 'build_trace_title', 'build_trace_detail', 'created_at', 'isoformat']
      varnames: ['.0', 'event']
      cellvars: []
      freevars: []
      disassembly:
      261           0 RETURN_GENERATOR
                    2 POP_TOP
                    4 RESUME                   0
                    6 LOAD_FAST                0 (.0)
      
      270     >>    8 FOR_ITER               112 (to 236)
                   12 STORE_FAST               1 (event)
      
      262          14 LOAD_GLOBAL              1 (NULL + SessionTraceEntry)
      
      263          24 LOAD_FAST                1 (event)
                   26 LOAD_ATTR                2 (event_id)
      
      264          46 LOAD_FAST                1 (event)
                   48 LOAD_ATTR                4 (event_type)
                   68 LOAD_ATTR                6 (value)
      
      265          88 LOAD_GLOBAL              9 (NULL + build_trace_step)
                   98 LOAD_FAST                1 (event)
                  100 LOAD_ATTR                4 (event_type)
                  120 CALL                     1
      
      266         128 LOAD_GLOBAL             11 (NULL + build_trace_title)
                  138 LOAD_FAST                1 (event)
                  140 CALL                     1
      
      267         148 LOAD_GLOBAL             13 (NULL + build_trace_detail)
                  158 LOAD_FAST                1 (event)
                  160 CALL                     1
      
      268         168 LOAD_FAST                1 (event)
                  170 LOAD_ATTR               14 (created_at)
                  190 LOAD_ATTR               17 (NULL|self + isoformat)
                  210 CALL                     0
      
      262         218 KW_NAMES                 0 (('event_id', 'event_type', 'step', 'title', 'detail', 'created_at'))
                  220 CALL                     6
                  228 YIELD_VALUE              1
                  230 RESUME                   1
                  232 POP_TOP
                  234 JUMP_BACKWARD          114 (to 8)
      
      270     >>  236 END_FOR
                  238 RETURN_CONST             1 (None)
              >>  240 CALL_INTRINSIC_1         3 (INTRINSIC_STOPITERATION_ERROR)
                  242 RERAISE                  1
      ExceptionTable:
        4 to 238 -> 240 [0] lasti

